{
  "date": "2026/07/07",
  "mode": "normal",
  "market_summary": "おはようございます、かぶぼっちです。日経平均は▼1,481円と派手に沈み、68,256円で着地。SOX-4.3%という半導体のナイアガラがトドメを刺した格好です。ただVIX15.9と恐怖指数は冷静で、市場全体がパニックというより『選別祭り』の様相。円は161.84円と輸出株には追い風が残っており、全面壊滅ではなく二極化相場と見るのがかぶぼっちの見立てです。",
  "nikkei": 68256,
  "nikkei_diff": -1481,
  "nikkei_pct": -2.1236933048453475,
  "usd_jpy": 161.84,
  "sox_pct": -4.258599126417524,
  "sox": 12350.8,
  "vix": 15.9,
  "topix": 4185.0,
  "topix_pct": -2.67,
  "nasdaq": 25940.9,
  "nasdaq_pct": -0.69,
  "sp500": 7527.9,
  "sp500_pct": -0.13,
  "news": [
    {
      "tag": "警戒",
      "headline": "SOX-4.3%の衝撃波、半導体セクターに防空壕が必要な朝",
      "body": "フィラデルフィア半導体指数が4%超の下落を記録し、東京エレクトロンやファナックなど国内半導体・FA関連銘柄に売りが波及。ただしVIX15.9水準はシステミックリスクを示唆しておらず、セクター固有の調整である可能性がある。半導体の嵐が全市場を飲み込むかどうかは、本日の米国市場の動向を確認してから判断するのが賢明との見方もある。"
    },
    {
      "tag": "チャンス",
      "headline": "下げ相場の中に宝あり、金融・消費が逆行高で存在感",
      "body": "三菱UFJやソニーグループが+2.3%、リクルートHDが+3.4%と日経急落の中で逆行高を演じており、セクターローテーションの匂いが漂う。内需・金融・ヘルスケアへの資金シフトが起きている可能性があり、銘柄選別次第でプラスリターンを狙える地合いとの見方もある。下げ相場こそ銘柄の質が問われる、まさに今日の格言通りの展開だ。"
    },
    {
      "tag": "米国",
      "headline": "ドル円161.84円維持、輸出株の下支えとなるか",
      "body": "ドル円は161円台後半を維持しており、円安メリットを享受できる輸出企業には収益面での追い風が続いている可能性がある。一方でトヨタ・ホンダなど自動車株は関税リスクとのせめぎ合いが続いており、単純な円安=自動車買いとはならない局面との見方もある。為替の水準を確認しつつ、個別のファンダメンタルズを精査する姿勢が求められる。"
    },
    {
      "tag": "日本",
      "headline": "ダイキン・リクルートにRSI過熱サイン、高値掴みに要警戒",
      "body": "ダイキンのRSI83.6、リクルートHDのRSI75.3はいずれも買われ過ぎ圏に突入しており、テクニカル的な調整リスクを内包している可能性がある。相場急落の日に逆行高を演じた銘柄は翌日以降の利確売りに注意が必要との見方もある。追いかけ買いは慎重に、押し目を待つ姿勢が結果的に報われやすい局面と言えそうだ。"
    }
  ],
  "stocks_jp": [
    {
      "pattern": "暴落リバウンド",
      "code": "9984",
      "name": "ソフトバンクG",
      "score": 7,
      "entry": "MA25乖離-13.9%・RSI33.5付近・BB下限タッチを確認後",
      "target": "+4%",
      "stop": "-3%",
      "reason": "RSI33.5はほぼ売られ過ぎ圏に到達し、BB下限に張り付いた状態。MA25からの乖離-13.9%は短期的な戻りの余地があるとの見方もできるが、AI投資コスト増加懸念という構造的な重しも残るため、リバウンド確認後のエントリーが原則。本日の米国ナスダックの反応を見てから判断するのが賢明。",
      "comment": "底かどうかは神のみぞ知る。でも-14%乖離は『安売りセール』の看板に見えなくもない🏷️",
      "ai_score": 44,
      "rsi": 33.5,
      "vol_ratio": 0.82
    },
    {
      "pattern": "セクターローテーション",
      "code": "8306",
      "name": "三菱UFJ",
      "score": 8,
      "entry": "本日の強さを確認後、RSI65以下への小幅調整場面",
      "target": "+3%",
      "stop": "-2%",
      "reason": "半導体・グロース売り→金融バリューへの資金ローテーションが起きている可能性があり、本日+2.3%の逆行高がその証左との見方もある。MA25乖離+6.2%と過熱感が出始めているため、飛びつき買いは避け、押し目を丁寧に拾う戦略が有効。RSIがまだ64.7と極端な過熱域ではなく、もう一段の上昇余地があるとの見方もある。",
      "comment": "金融株が輝く日は、どこかで誰かが泣いている相場の法則通りだ💴",
      "ai_score": 48,
      "rsi": 64.7,
      "vol_ratio": 0.85
    },
    {
      "pattern": "モメンタム",
      "code": "6758",
      "name": "ソニーグループ",
      "score": 7,
      "entry": "BB上限付近での勢い継続確認後・RSI65以下への調整場面",
      "target": "+3%",
      "stop": "-2%",
      "reason": "本日+2.3%の上昇でMA25乖離+4.9%・RSI64.7と強いモメンタムを示しているが、BB上限に達しており短期的な過熱感も否定できない。エンタメ・半導体両軸の事業構造がSOX下落の影響を受けるリスクもあるため、勢いに乗りつつも適切な損切設定が不可欠。押し目があれば積極的に検討したい銘柄の一つとの見方もある。",
      "comment": "ソニーはゲームも映画もAIも、事業の多さが今日は武器になっている🎮",
      "ai_score": 47,
      "rsi": 64.7,
      "vol_ratio": 0.95
    },
    {
      "pattern": "押し目買い",
      "code": "6954",
      "name": "ファナック",
      "score": 6,
      "entry": "MA25乖離-3.7%付近・RSI40-45水準での下げ止まり確認後",
      "target": "+3%",
      "stop": "-2%",
      "reason": "SOX-4.3%の余波で-5.4%と大きく下げたが、MA25乖離-3.7%・RSI44.5とテクニカル的には中立圏に近づきつつある。FA・ロボット需要の長期トレンドは変わらないとの見方もあり、短期的な半導体ショックによる売られ過ぎからのリバウンドを狙う押し目買い候補として浮上。底打ち確認前のナンピンは厳禁で、陽線確認後のエントリーが原則。",
      "comment": "工場自動化の王者が5%安でセール中。でも嵐の中での買い方は慎重に🤖",
      "ai_score": 51,
      "rsi": 44.5,
      "vol_ratio": 0.8
    },
    {
      "pattern": "井村式急回復",
      "code": "6501",
      "name": "日立製作所",
      "score": 7,
      "entry": "本日+2.9%の上昇後、MA25+3.5%・RSI57.7付近への小幅調整場面",
      "target": "+3%",
      "stop": "-2%",
      "reason": "日経急落の中で+2.9%の逆行高を演じており、インフラ・デジタル事業を軸とした事業変革への評価が底堅さを支えている可能性がある。RSI57.7・MA25乖離+3.5%と過熱感は限定的で、まだ上昇余地があるとの見方もある。押し目での買い増しを視野に入れつつ、損切ラインを明確にした上でのエントリーを推奨。",
      "comment": "昔の日立と今の日立は別物。変革した会社は相場の嵐に強い傾向がある⚡",
      "ai_score": 58,
      "rsi": 57.7,
      "vol_ratio": 1.02
    }
  ],
  "stock_us": {
    "pattern": "バフェット式",
    "ticker": "$NVDA",
    "name": "エヌビディア",
    "score": 7,
    "entry": "SOX急落後の下げ一服・RSI40以下への調整場面を確認後",
    "target": "+5%",
    "stop": "-3%",
    "reason": "SOX-4.3%の主因の一つとして半導体全体が売られる中、エヌビディアのAIインフラ需要という長期テーマは変わらないとの見方もある。短期的な過熱修正が続く可能性はあるが、押し目を丁寧に拾う長期視点ではバフェット式の割安探しの対象として浮上しうる局面との見方もある。本日の米国市場の動向を必ず確認してからエントリーを検討すること。",
    "comment": "嵐の後に虹が出るかどうかは神のみぞ知る。でもAIの波は止まらないという見方もある🌈"
  },
  "consideration": {
    "main": "本日の相場を一言で表すなら『嵐の中の二極化』。日経▼1,481円という大波が全体を飲み込む中、金融・内需・ヘルスケアは浮き輪をつけて漂っている。SOX-4.3%は半導体に直接打撃を与えたが、VIX15.9という低水準はパニック売りではなくセクター選別の動きである可能性を示唆している。今日の戦場は全面買いでも全面空売りでもなく、どのセクターに資金が向かっているかを読む『探偵の目』が必要。逆行高の金融・消費を追うか、売られ過ぎの半導体・FA系のリバウンドを待つか、二つの戦略を同時に持つのがかぶぼっち流の対処法だ。",
    "point": "下げ相場でも上がった銘柄の『なぜ』を解明することが今日最大のテーマ。",
    "action": "逆行高銘柄のセクターを確認し、資金ローテーションの方向性を把握した上で、押し目エントリーの水準をあらかじめ設定しておく。"
  },
  "surges": [
    {
      "code": "9022",
      "name": "東海旅客鉄道",
      "pct": 3.96,
      "price": 3700
    },
    {
      "code": "6098",
      "name": "リクルートH",
      "pct": 3.4,
      "price": 12300
    },
    {
      "code": "8604",
      "name": "野村HD",
      "pct": 3.02,
      "price": 1535
    }
  ],
  "drops": [
    {
      "code": "6920",
      "name": "レーザーテック",
      "pct": -6.36,
      "price": 44050
    },
    {
      "code": "6954",
      "name": "ファナック",
      "pct": -5.42,
      "price": 7072
    },
    {
      "code": "6273",
      "name": "SMC",
      "pct": -4.29,
      "price": 72540
    },
    {
      "code": "8035",
      "name": "東京エレクトロン",
      "pct": -3.94,
      "price": 69470
    },
    {
      "code": "9984",
      "name": "ソフトバンクG",
      "pct": -3.48,
      "price": 5771
    }
  ],
  "sector_heatmap": [
    {
      "sector": "サービス",
      "avg_pct": 2.7,
      "count": 2,
      "up": 2,
      "down": 0,
      "top_mover": {
        "name": "リクルートH",
        "code": "6098",
        "pct": 3.4
      }
    },
    {
      "sector": "不動産",
      "avg_pct": 1.75,
      "count": 2,
      "up": 2,
      "down": 0,
      "top_mover": {
        "name": "三菱地所",
        "code": "8802",
        "pct": 2.47
      }
    },
    {
      "sector": "ゲーム・娯楽",
      "avg_pct": 1.4,
      "count": 3,
      "up": 3,
      "down": 0,
      "top_mover": {
        "name": "バンダイナムコHD",
        "code": "7832",
        "pct": 1.77
      }
    },
    {
      "sector": "医療機器",
      "avg_pct": 1.33,
      "count": 1,
      "up": 1,
      "down": 0,
      "top_mover": {
        "name": "テルモ",
        "code": "4543",
        "pct": 1.33
      }
    },
    {
      "sector": "運輸",
      "avg_pct": 1.09,
      "count": 3,
      "up": 2,
      "down": 1,
      "top_mover": {
        "name": "東海旅客鉄道",
        "code": "9022",
        "pct": 3.96
      }
    },
    {
      "sector": "金融",
      "avg_pct": 0.93,
      "count": 5,
      "up": 4,
      "down": 1,
      "top_mover": {
        "name": "野村HD",
        "code": "8604",
        "pct": 3.02
      }
    },
    {
      "sector": "生活必需品",
      "avg_pct": 0.49,
      "count": 5,
      "up": 4,
      "down": 1,
      "top_mover": {
        "name": "キッコーマン",
        "code": "2801",
        "pct": 1.27
      }
    },
    {
      "sector": "商社",
      "avg_pct": 0.44,
      "count": 4,
      "up": 3,
      "down": 1,
      "top_mover": {
        "name": "住友商事",
        "code": "8053",
        "pct": 1.16
      }
    },
    {
      "sector": "通信・IT",
      "avg_pct": 0.35,
      "count": 6,
      "up": 5,
      "down": 1,
      "top_mover": {
        "name": "ソフトバンクG",
        "code": "9984",
        "pct": -3.48
      }
    },
    {
      "sector": "小売",
      "avg_pct": 0.12,
      "count": 3,
      "up": 2,
      "down": 1,
      "top_mover": {
        "name": "セブン&アイHD",
        "code": "3382",
        "pct": -1.25
      }
    },
    {
      "sector": "電機",
      "avg_pct": 0.05,
      "count": 6,
      "up": 3,
      "down": 3,
      "top_mover": {
        "name": "パナソニックHD",
        "code": "6752",
        "pct": -3.45
      }
    },
    {
      "sector": "自動車",
      "avg_pct": -0.29,
      "count": 5,
      "up": 2,
      "down": 3,
      "top_mover": {
        "name": "ホンダ",
        "code": "7267",
        "pct": -1.78
      }
    },
    {
      "sector": "医薬品",
      "avg_pct": -0.6,
      "count": 4,
      "up": 1,
      "down": 3,
      "top_mover": {
        "name": "第一三共",
        "code": "4568",
        "pct": -1.41
      }
    },
    {
      "sector": "エネルギー",
      "avg_pct": -0.88,
      "count": 2,
      "up": 0,
      "down": 2,
      "top_mover": {
        "name": "ENEOSホールディングス",
        "code": "5020",
        "pct": -0.91
      }
    },
    {
      "sector": "精密機器",
      "avg_pct": -0.95,
      "count": 2,
      "up": 1,
      "down": 1,
      "top_mover": {
        "name": "キーエンス",
        "code": "6861",
        "pct": -3.37
      }
    },
    {
      "sector": "素材",
      "avg_pct": -1.36,
      "count": 4,
      "up": 1,
      "down": 3,
      "top_mover": {
        "name": "信越化学",
        "code": "4063",
        "pct": -3.47
      }
    },
    {
      "sector": "建設",
      "avg_pct": -1.56,
      "count": 1,
      "up": 0,
      "down": 1,
      "top_mover": {
        "name": "大成建設",
        "code": "1801",
        "pct": -1.56
      }
    },
    {
      "sector": "機械",
      "avg_pct": -2.74,
      "count": 4,
      "up": 0,
      "down": 4,
      "top_mover": {
        "name": "ファナック",
        "code": "6954",
        "pct": -5.42
      }
    },
    {
      "sector": "半導体",
      "avg_pct": -2.96,
      "count": 4,
      "up": 1,
      "down": 3,
      "top_mover": {
        "name": "レーザーテック",
        "code": "6920",
        "pct": -6.36
      }
    }
  ],
  "jp_top_movers": [
    {
      "code": "6920",
      "name": "レーザーテック",
      "pct": -6.36,
      "price": 44050,
      "sector": "半導体"
    },
    {
      "code": "6954",
      "name": "ファナック",
      "pct": -5.42,
      "price": 7072,
      "sector": "機械"
    },
    {
      "code": "6273",
      "name": "SMC",
      "pct": -4.29,
      "price": 72540,
      "sector": "機械"
    },
    {
      "code": "9022",
      "name": "東海旅客鉄道",
      "pct": 3.96,
      "price": 3700,
      "sector": "運輸"
    },
    {
      "code": "8035",
      "name": "東京エレクトロン",
      "pct": -3.94,
      "price": 69470,
      "sector": "半導体"
    },
    {
      "code": "9984",
      "name": "ソフトバンクG",
      "pct": -3.48,
      "price": 5771,
      "sector": "通信・IT"
    },
    {
      "code": "4063",
      "name": "信越化学",
      "pct": -3.47,
      "price": 7158,
      "sector": "素材"
    },
    {
      "code": "6752",
      "name": "パナソニックHD",
      "pct": -3.45,
      "price": 4400,
      "sector": "電機"
    },
    {
      "code": "6098",
      "name": "リクルートH",
      "pct": 3.4,
      "price": 12300,
      "sector": "サービス"
    },
    {
      "code": "6861",
      "name": "キーエンス",
      "pct": -3.37,
      "price": 78180,
      "sector": "精密機器"
    }
  ],
  "jp_all_changes": [
    {
      "code": "7203",
      "name": "トヨタ自動車",
      "pct": 0.79,
      "price": 2946,
      "sector": "自動車"
    },
    {
      "code": "9984",
      "name": "ソフトバンクG",
      "pct": -3.48,
      "price": 5771,
      "sector": "通信・IT"
    },
    {
      "code": "6758",
      "name": "ソニーG",
      "pct": 2.34,
      "price": 3502,
      "sector": "電機"
    },
    {
      "code": "6861",
      "name": "キーエンス",
      "pct": -3.37,
      "price": 78180,
      "sector": "精密機器"
    },
    {
      "code": "8306",
      "name": "三菱UFJ",
      "pct": 2.26,
      "price": 3446,
      "sector": "金融"
    },
    {
      "code": "9432",
      "name": "NTT",
      "pct": 0.68,
      "price": 148,
      "sector": "通信・IT"
    },
    {
      "code": "4063",
      "name": "信越化学",
      "pct": -3.47,
      "price": 7158,
      "sector": "素材"
    },
    {
      "code": "6954",
      "name": "ファナック",
      "pct": -5.42,
      "price": 7072,
      "sector": "機械"
    },
    {
      "code": "8035",
      "name": "東京エレクトロン",
      "pct": -3.94,
      "price": 69470,
      "sector": "半導体"
    },
    {
      "code": "6367",
      "name": "ダイキン工業",
      "pct": -0.65,
      "price": 25980,
      "sector": "機械"
    },
    {
      "code": "8058",
      "name": "三菱商事",
      "pct": -0.16,
      "price": 4500,
      "sector": "商社"
    },
    {
      "code": "6098",
      "name": "リクルートH",
      "pct": 3.4,
      "price": 12300,
      "sector": "サービス"
    },
    {
      "code": "7974",
      "name": "任天堂",
      "pct": 1.64,
      "price": 7148,
      "sector": "ゲーム・娯楽"
    },
    {
      "code": "4568",
      "name": "第一三共",
      "pct": -1.41,
      "price": 2719,
      "sector": "医薬品"
    },
    {
      "code": "9983",
      "name": "ファーストリテイリング",
      "pct": 1.12,
      "price": 87900,
      "sector": "小売"
    },
    {
      "code": "6501",
      "name": "日立製作所",
      "pct": 2.85,
      "price": 4942,
      "sector": "電機"
    },
    {
      "code": "7267",
      "name": "ホンダ",
      "pct": -1.78,
      "price": 1570,
      "sector": "自動車"
    },
    {
      "code": "2914",
      "name": "JT",
      "pct": 0.48,
      "price": 6219,
      "sector": "生活必需品"
    },
    {
      "code": "4543",
      "name": "テルモ",
      "pct": 1.33,
      "price": 2324,
      "sector": "医療機器"
    },
    {
      "code": "4519",
      "name": "中外製薬",
      "pct": 1.05,
      "price": 7620,
      "sector": "医薬品"
    },
    {
      "code": "6857",
      "name": "アドバンテスト",
      "pct": -2.25,
      "price": 28900,
      "sector": "半導体"
    },
    {
      "code": "6920",
      "name": "レーザーテック",
      "pct": -6.36,
      "price": 44050,
      "sector": "半導体"
    },
    {
      "code": "4452",
      "name": "花王",
      "pct": -0.78,
      "price": 3301,
      "sector": "生活必需品"
    },
    {
      "code": "9433",
      "name": "KDDI",
      "pct": 1.52,
      "price": 2779,
      "sector": "通信・IT"
    },
    {
      "code": "8316",
      "name": "三井住友FG",
      "pct": 0.18,
      "price": 6812,
      "sector": "金融"
    },
    {
      "code": "7751",
      "name": "キヤノン",
      "pct": -0.51,
      "price": 4316,
      "sector": "電機"
    },
    {
      "code": "4901",
      "name": "富士フイルム",
      "pct": 0.66,
      "price": 3646,
      "sector": "電機"
    },
    {
      "code": "6702",
      "name": "富士通",
      "pct": 1.28,
      "price": 3392,
      "sector": "通信・IT"
    },
    {
      "code": "9022",
      "name": "東海旅客鉄道",
      "pct": 3.96,
      "price": 3700,
      "sector": "運輸"
    },
    {
      "code": "8802",
      "name": "三菱地所",
      "pct": 2.47,
      "price": 4358,
      "sector": "不動産"
    },
    {
      "code": "7201",
      "name": "日産自動車",
      "pct": 0.85,
      "price": 321,
      "sector": "自動車"
    },
    {
      "code": "7269",
      "name": "スズキ",
      "pct": -0.7,
      "price": 2129,
      "sector": "自動車"
    },
    {
      "code": "7270",
      "name": "SUBARU",
      "pct": -0.62,
      "price": 2573,
      "sector": "自動車"
    },
    {
      "code": "4689",
      "name": "LINEヤフー",
      "pct": 1.46,
      "price": 445,
      "sector": "通信・IT"
    },
    {
      "code": "4307",
      "name": "野村総合研究所",
      "pct": 0.63,
      "price": 5119,
      "sector": "通信・IT"
    },
    {
      "code": "6503",
      "name": "三菱電機",
      "pct": -1.59,
      "price": 5947,
      "sector": "電機"
    },
    {
      "code": "6752",
      "name": "パナソニックHD",
      "pct": -3.45,
      "price": 4400,
      "sector": "電機"
    },
    {
      "code": "7733",
      "name": "オリンパス",
      "pct": 1.47,
      "price": 1790,
      "sector": "精密機器"
    },
    {
      "code": "8411",
      "name": "みずほFG",
      "pct": 0.39,
      "price": 8227,
      "sector": "金融"
    },
    {
      "code": "8604",
      "name": "野村HD",
      "pct": 3.02,
      "price": 1535,
      "sector": "金融"
    },
    {
      "code": "8766",
      "name": "東京海上HD",
      "pct": -1.2,
      "price": 7716,
      "sector": "金融"
    },
    {
      "code": "5401",
      "name": "日本製鉄",
      "pct": 0.23,
      "price": 560,
      "sector": "素材"
    },
    {
      "code": "4188",
      "name": "三菱ケミカルG",
      "pct": -1.16,
      "price": 1193,
      "sector": "素材"
    },
    {
      "code": "3407",
      "name": "旭化成",
      "pct": -1.03,
      "price": 1881,
      "sector": "素材"
    },
    {
      "code": "6301",
      "name": "コマツ",
      "pct": -0.58,
      "price": 6710,
      "sector": "機械"
    },
    {
      "code": "6273",
      "name": "SMC",
      "pct": -4.29,
      "price": 72540,
      "sector": "機械"
    },
    {
      "code": "6723",
      "name": "ルネサスエレクトロニクス",
      "pct": 0.72,
      "price": 4744,
      "sector": "半導体"
    },
    {
      "code": "8031",
      "name": "三井物産",
      "pct": 0.21,
      "price": 4677,
      "sector": "商社"
    },
    {
      "code": "8001",
      "name": "伊藤忠商事",
      "pct": 0.55,
      "price": 1904,
      "sector": "商社"
    },
    {
      "code": "8053",
      "name": "住友商事",
      "pct": 1.16,
      "price": 1609,
      "sector": "商社"
    },
    {
      "code": "4755",
      "name": "楽天G",
      "pct": 2.0,
      "price": 792,
      "sector": "サービス"
    },
    {
      "code": "9697",
      "name": "カプコン",
      "pct": 0.79,
      "price": 3325,
      "sector": "ゲーム・娯楽"
    },
    {
      "code": "7832",
      "name": "バンダイナムコHD",
      "pct": 1.77,
      "price": 4078,
      "sector": "ゲーム・娯楽"
    },
    {
      "code": "4502",
      "name": "武田薬品工業",
      "pct": -1.25,
      "price": 5448,
      "sector": "医薬品"
    },
    {
      "code": "4523",
      "name": "エーザイ",
      "pct": -0.81,
      "price": 4305,
      "sector": "医薬品"
    },
    {
      "code": "3382",
      "name": "セブン&アイHD",
      "pct": -1.25,
      "price": 2057,
      "sector": "小売"
    },
    {
      "code": "8267",
      "name": "イオン",
      "pct": 0.48,
      "price": 1462,
      "sector": "小売"
    },
    {
      "code": "2502",
      "name": "アサヒグループHD",
      "pct": 0.53,
      "price": 1610,
      "sector": "生活必需品"
    },
    {
      "code": "2503",
      "name": "キリンHD",
      "pct": 0.97,
      "price": 2876,
      "sector": "生活必需品"
    },
    {
      "code": "2801",
      "name": "キッコーマン",
      "pct": 1.27,
      "price": 1678,
      "sector": "生活必需品"
    },
    {
      "code": "9020",
      "name": "東日本旅客鉄道",
      "pct": 1.48,
      "price": 3554,
      "sector": "運輸"
    },
    {
      "code": "9101",
      "name": "日本郵船",
      "pct": -2.18,
      "price": 5253,
      "sector": "運輸"
    },
    {
      "code": "8801",
      "name": "三井不動産",
      "pct": 1.03,
      "price": 1571,
      "sector": "不動産"
    },
    {
      "code": "5020",
      "name": "ENEOSホールディングス",
      "pct": -0.91,
      "price": 1248,
      "sector": "エネルギー"
    },
    {
      "code": "1605",
      "name": "INPEX",
      "pct": -0.85,
      "price": 3281,
      "sector": "エネルギー"
    },
    {
      "code": "1801",
      "name": "大成建設",
      "pct": -1.56,
      "price": 14870,
      "sector": "建設"
    }
  ],
  "us_sector_heatmap": [
    {
      "sector": "ヘルスケア",
      "avg_pct": 2.65,
      "count": 3,
      "up": 3,
      "down": 0,
      "top_mover": {
        "name": "Eli Lilly",
        "code": "LLY",
        "pct": 3.32
      }
    },
    {
      "sector": "エネルギー",
      "avg_pct": 2.62,
      "count": 2,
      "up": 2,
      "down": 0,
      "top_mover": {
        "name": "ExxonMobil",
        "code": "XOM",
        "pct": 2.89
      }
    },
    {
      "sector": "生活必需品",
      "avg_pct": 2.11,
      "count": 3,
      "up": 3,
      "down": 0,
      "top_mover": {
        "name": "Procter & Gamble",
        "code": "PG",
        "pct": 2.6
      }
    },
    {
      "sector": "通信・メディア",
      "avg_pct": 1.52,
      "count": 3,
      "up": 3,
      "down": 0,
      "top_mover": {
        "name": "Meta Platforms",
        "code": "META",
        "pct": 2.31
      }
    },
    {
      "sector": "テクノロジー",
      "avg_pct": 0.81,
      "count": 3,
      "up": 2,
      "down": 1,
      "top_mover": {
        "name": "Alphabet",
        "code": "GOOGL",
        "pct": 1.5
      }
    },
    {
      "sector": "消費・EC",
      "avg_pct": 0.54,
      "count": 3,
      "up": 2,
      "down": 1,
      "top_mover": {
        "name": "Walmart",
        "code": "WMT",
        "pct": 1.9
      }
    },
    {
      "sector": "金融",
      "avg_pct": 0.54,
      "count": 3,
      "up": 2,
      "down": 1,
      "top_mover": {
        "name": "Bank of America",
        "code": "BAC",
        "pct": 1.07
      }
    },
    {
      "sector": "資本財",
      "avg_pct": -2.35,
      "count": 3,
      "up": 0,
      "down": 3,
      "top_mover": {
        "name": "Caterpillar",
        "code": "CAT",
        "pct": -4.0
      }
    },
    {
      "sector": "半導体",
      "avg_pct": -3.3,
      "count": 3,
      "up": 0,
      "down": 3,
      "top_mover": {
        "name": "AMD",
        "code": "AMD",
        "pct": -6.4
      }
    }
  ],
  "us_top_movers": [
    {
      "code": "AMD",
      "name": "AMD",
      "pct": -6.4,
      "price": 516.73,
      "sector": "半導体"
    },
    {
      "code": "CAT",
      "name": "Caterpillar",
      "pct": -4.0,
      "price": 931.12,
      "sector": "資本財"
    },
    {
      "code": "LLY",
      "name": "Eli Lilly",
      "pct": 3.32,
      "price": 1239.88,
      "sector": "ヘルスケア"
    },
    {
      "code": "JNJ",
      "name": "Johnson & Johnson",
      "pct": 3.14,
      "price": 267.46,
      "sector": "ヘルスケア"
    },
    {
      "code": "XOM",
      "name": "ExxonMobil",
      "pct": 2.89,
      "price": 140.38,
      "sector": "エネルギー"
    },
    {
      "code": "PG",
      "name": "Procter & Gamble",
      "pct": 2.6,
      "price": 153.19,
      "sector": "生活必需品"
    },
    {
      "code": "GE",
      "name": "GE Aerospace",
      "pct": -2.51,
      "price": 369.16,
      "sector": "資本財"
    },
    {
      "code": "KO",
      "name": "Coca-Cola",
      "pct": 2.39,
      "price": 84.94,
      "sector": "生活必需品"
    },
    {
      "code": "CVX",
      "name": "Chevron",
      "pct": 2.36,
      "price": 172.07,
      "sector": "エネルギー"
    },
    {
      "code": "META",
      "name": "Meta Platforms",
      "pct": 2.31,
      "price": 614.18,
      "sector": "通信・メディア"
    }
  ],
  "us_all_changes": [
    {
      "code": "AAPL",
      "name": "Apple",
      "pct": -0.32,
      "price": 311.65,
      "sector": "テクノロジー"
    },
    {
      "code": "MSFT",
      "name": "Microsoft",
      "pct": 1.24,
      "price": 391.55,
      "sector": "テクノロジー"
    },
    {
      "code": "GOOGL",
      "name": "Alphabet",
      "pct": 1.5,
      "price": 371.97,
      "sector": "テクノロジー"
    },
    {
      "code": "NVDA",
      "name": "NVIDIA",
      "pct": -1.73,
      "price": 192.17,
      "sector": "半導体"
    },
    {
      "code": "AMD",
      "name": "AMD",
      "pct": -6.4,
      "price": 516.73,
      "sector": "半導体"
    },
    {
      "code": "AVGO",
      "name": "Broadcom",
      "pct": -1.78,
      "price": 367.23,
      "sector": "半導体"
    },
    {
      "code": "AMZN",
      "name": "Amazon",
      "pct": 0.94,
      "price": 246.46,
      "sector": "消費・EC"
    },
    {
      "code": "TSLA",
      "name": "Tesla",
      "pct": -1.21,
      "price": 414.7,
      "sector": "消費・EC"
    },
    {
      "code": "WMT",
      "name": "Walmart",
      "pct": 1.9,
      "price": 112.75,
      "sector": "消費・EC"
    },
    {
      "code": "META",
      "name": "Meta Platforms",
      "pct": 2.31,
      "price": 614.18,
      "sector": "通信・メディア"
    },
    {
      "code": "NFLX",
      "name": "Netflix",
      "pct": 1.14,
      "price": 76.89,
      "sector": "通信・メディア"
    },
    {
      "code": "DIS",
      "name": "Disney",
      "pct": 1.11,
      "price": 98.49,
      "sector": "通信・メディア"
    },
    {
      "code": "JPM",
      "name": "JPMorgan Chase",
      "pct": 0.91,
      "price": 340.78,
      "sector": "金融"
    },
    {
      "code": "BAC",
      "name": "Bank of America",
      "pct": 1.07,
      "price": 60.54,
      "sector": "金融"
    },
    {
      "code": "GS",
      "name": "Goldman Sachs",
      "pct": -0.36,
      "price": 1051.44,
      "sector": "金融"
    },
    {
      "code": "JNJ",
      "name": "Johnson & Johnson",
      "pct": 3.14,
      "price": 267.46,
      "sector": "ヘルスケア"
    },
    {
      "code": "UNH",
      "name": "UnitedHealth",
      "pct": 1.49,
      "price": 424.23,
      "sector": "ヘルスケア"
    },
    {
      "code": "LLY",
      "name": "Eli Lilly",
      "pct": 3.32,
      "price": 1239.88,
      "sector": "ヘルスケア"
    },
    {
      "code": "XOM",
      "name": "ExxonMobil",
      "pct": 2.89,
      "price": 140.38,
      "sector": "エネルギー"
    },
    {
      "code": "CVX",
      "name": "Chevron",
      "pct": 2.36,
      "price": 172.07,
      "sector": "エネルギー"
    },
    {
      "code": "KO",
      "name": "Coca-Cola",
      "pct": 2.39,
      "price": 84.94,
      "sector": "生活必需品"
    },
    {
      "code": "PG",
      "name": "Procter & Gamble",
      "pct": 2.6,
      "price": 153.19,
      "sector": "生活必需品"
    },
    {
      "code": "COST",
      "name": "Costco",
      "pct": 1.33,
      "price": 962.93,
      "sector": "生活必需品"
    },
    {
      "code": "BA",
      "name": "Boeing",
      "pct": -0.53,
      "price": 233.29,
      "sector": "資本財"
    },
    {
      "code": "CAT",
      "name": "Caterpillar",
      "pct": -4.0,
      "price": 931.12,
      "sector": "資本財"
    },
    {
      "code": "GE",
      "name": "GE Aerospace",
      "pct": -2.51,
      "price": 369.16,
      "sector": "資本財"
    }
  ],
  "events_jp": [
    {
      "date": "2026-07-07",
      "text": "5月毎月勤労統計・現金給与総額発表（賃金動向の確認、日銀政策への影響注目）",
      "importance": "medium",
      "urgent": false
    },
    {
      "date": "2026-07-08",
      "text": "5月国際収支・経常収支発表",
      "importance": "low",
      "urgent": false
    },
    {
      "date": "2026-07-10",
      "text": "5月機械受注発表（設備投資動向の先行指標・FA・ロボット関連への影響注目）",
      "importance": "medium",
      "urgent": false
    },
    {
      "date": "2026-07-14",
      "text": "日銀金融政策決定会合（1日目）・政策金利・経済・物価情勢の展望に関する発表予定",
      "importance": "high",
      "urgent": true
    },
    {
      "date": "2026-07-15",
      "text": "日銀金融政策決定会合（2日目）・政策金利決定・植田総裁記者会見",
      "importance": "high",
      "urgent": true
    }
  ],
  "events_us": [
    {
      "date": "2026-07-07",
      "text": "6月ISM非製造業景況指数発表（景気動向の確認・FRB政策への影響注目）",
      "importance": "medium",
      "urgent": false
    },
    {
      "date": "2026-07-08",
      "text": "6月ADP全国雇用者数発表（雇用統計の前哨戦・市場の注目度高）",
      "importance": "medium",
      "urgent": false
    },
    {
      "date": "2026-07-10",
      "text": "6月米雇用統計発表（非農業部門雇用者数・失業率・平均時給・FRB利下げ判断に直結）",
      "importance": "high",
      "urgent": true
    },
    {
      "date": "2026-07-15",
      "text": "6月米消費者物価指数（CPI）発表・インフレ動向・FRB政策判断への影響大",
      "importance": "high",
      "urgent": true
    },
    {
      "date": "2026-07-16",
      "text": "6月米小売売上高発表・個人消費動向の確認",
      "importance": "medium",
      "urgent": false
    }
  ],
  "x_posts": [
    "【🌀7/7 朝の相場速報】\n日経▼1,481円(-2.12%)・68,256円着地💥\nSOX-4.3%の半導体ナイアガラが直撃\nでもVIX15.9と恐怖指数は冷静😌\n\n金融・内需が逆行高→セクターローテーション勃発の可能性\n嵐の中でも光る銘柄を探す目が問われる朝\n\n詳細分析はnoteで👇\n#日本株 #日経平均 #スイングトレード",
    "【📊本日の注目銘柄】かぶぼっち的ピックアップ\n\n🔴ソフトバンクG(9984)\nRSI33.5・MA25乖離-13.9%でほぼ売られ過ぎ圏\n『底かどうかは神のみぞ知る。でも-14%乖離は安売りセールの看板に見えなくもない』\n\n🟢三菱UFJ(8306)\n日経急落の中+2.3%逆行高\nセクターローテーションの旗手候補\n\n追いかけず・確認してから😤\n#スイングトレード #日本株",
    "【🤔今日のかぶぼっち的問いかけ】\n\n日経▼1,481円の暴落日に\nあなたはどの銘柄に注目してる？\n\nA: 半導体系の反発狙い\nB: 金融の逆行高に乗る\nC: 全部売ってキャッシュポジション\nD: そもそも今日は見ない\n\n相場の嵐こそ、戦略の差が出る日🌪️\nコメントで教えてね👇\n#日本株 #日経平均"
  ],
  "note_body": "# 【7/7朝刊】日経▼1,481円の嵐の中に宝を探せ｜かぶぼっちの朝市場分析\n\n## リード：今日の相場を一言で\n\n**「全面安ではなく選別祭り。下げ相場こそ銘柄眼力が試される日。」**\n\n---\n\n## 今日の相場ポイント｜昨夜から今朝にかけての重要情報\n\nおはようございます、かぶぼっちです。2026年7月7日（火）の朝市場を読み解いていきます。\n\n日経平均は▼1,481円（-2.12%）と大幅下落し、68,256円で前日取引を終えました。主犯はSOX指数（フィラデルフィア半導体指数）の-4.3%という急落で、半導体関連銘柄に容赦ない売りが波及した格好です。\n\n**為替（USD/JPY）は161.84円**と円安水準を維持。一見すると輸出株への追い風のはずですが、自動車株への関税リスクという構造的な問題が混在しており、単純な円安恩恵とは言い切れない局面との見方もあります。\n\n注目すべきは**VIX（恐怖指数）が15.9**という低水準にとどまっていること。市場全体がパニックに陥っているわけではなく、半導体・グロース系からバリュー・内需・金融へのセクターローテーションが起きている可能性を示唆しています。三菱UFJ(8306)+2.3%、ソニーグループ(6758)+2.3%、リクルートHD(6098)+3.4%など、日経急落の日に逆行高を演じた銘柄が散見されるのはその証左との見方もできます。\n\n**今日のテーマは「どこに資金が流れているかを読む」こと。**全面売りでも全面買いでもなく、勝者と敗者が明確に分かれる「選別相場」です。\n\n**注意点：** SOX急落の余波が本日の東京市場にも引き続き影響する可能性があり、半導体・FA関連銘柄のリバウンドを狙う場合は底打ち確認が必須です。本日の米国市場（夜間）の動向が明日の戦略を左右する可能性があります。\n\n---\n\n## 注目銘柄分析｜今日のかぶぼっちピックアップ\n\n### ①ソフトバンクG（9984）★★★☆☆　暴落リバウンド候補\n\n**現在値：5,771円 / -3.5%**\n\nRSI33.5・MA25乖離-13.9%・BB下限タッチというテクニカルの三重底シグナルが点灯中。売られ過ぎ圏に近づいており、短期的なリバウンドの可能性があるとの見方もあります。\n\n- **エントリー条件：** RSI30付近・BB下限タッチ後の陽線確認・出来高増加を確認後\n- **利確目安：** +4%程度\n- **損切ライン：** -3%\n- **注意点：** AI投資コスト増加懸念という構造的な重しが残るため、リバウンド確認前のナンピンは厳禁。本日の米国ナスダック動向を必ず確認してからエントリーを検討すること。\n\n---\n\n### ②三菱UFJ（8306）★★★★☆　セクターローテーション\n\n**現在値：3,446円 / +2.3%**\n\n日経急落の中での逆行高+2.3%は「お金の流れ」を示している可能性があります。MA25乖離+6.2%、RSI64.7と適度な強さを示しており、過熱感はまだ限定的との見方もできます。\n\n- **エントリー条件：** RSI60以下への小幅調整・MA25付近への押し目場面\n- **利確目安：** +3%程度\n- **損切ライン：** -2%\n- **注意点：** BB上限に到達しており、短期の利確売りには注意。飛びつき買いは避け、押し目を待つ姿勢が重要。\n\n---\n\n### ③ファナック（6954）★★★☆☆　押し目買い候補\n\n**現在値：7,072円 / -5.4%**\n\nSOX急落の余波で-5.4%と本日の下落率上位に入りましたが、MA25乖離-3.7%・RSI44.5と中立圏に近づきつつあります。FA・ロボット自動化という長期テーマは変わらないとの見方もあり、押し目買いの候補として注目しています。\n\n- **エントリー条件：** RSI40-45水準での下げ止まり確認・陽線転換後\n- **利確目安：** +3%程度\n- **損切ライン：** -2%\n- **注意点：** 半導体下落が継続する場合は連動リスクあり。底打ち確認前の買いは厳禁。\n\n---\n\n### ④日立製作所（6501）★★★★☆　井村式急回復\n\n**現在値：4,942円 / +2.9%**\n\n日経急落の中で+2.9%の逆行高は、事業変革（インフラ×デジタル）への市場評価が高まっている可能性を示唆します。RSI57.7・MA25乖離+3.5%と過熱感は限定的で、まだ上値余地があるとの見方もあります。\n\n- **エントリー条件：** 本日の強さを確認後、RSI55前後への小幅調整場面\n- **利確目安：** +3%程度\n- **損切ライン：** -2%\n- **注意点：** BB中間から上限へ移行中。強さを確認しつつも損切ラインは明確に設定すること。\n\n---\n\n### ⑤ソニーグループ（6758）★★★☆☆　モメンタム\n\n**現在値：3,502円 / +2.3%**\n\nエンタメ・半導体・金融サービスの多角的な事業構造が、SOX急落の中でも底堅さを演出した可能性があります。RSI64.7・MA25乖離+4.9%とモメンタムは強いが、BB上限に達しており短期的な調整には注意が必要です。\n\n- **エントリー条件：** BB上限からの小幅調整・RSI60以下への押し目確認後\n- **利確目安：** +3%程度\n- **損切ライン：** -2%\n- **注意点：** 半導体部門はSOX下落の影響を受けるリスクもあるため、米国市場の動向を確認することが重要。\n\n---\n\n## 今日の売買戦略\n\n**【デイトレ】** 逆行高継続中の金融・内需銘柄の午前中モメンタムを狙う。ただし日経先物の動向を常に確認し、全体相場に振られないよう損切ラインを必ず設定する。\n\n**【スイングトレード】** ソフトバンクGなど売られ過ぎ圏の銘柄は2〜3日スパンでのリバウンド狙いが検討できる可能性があるが、底打ち確認を最優先条件とする。日本株スイングトレードの基本は「確認してから乗る」。\n\n**【中長期】** ファナックや日立など日本の製造業DXを担う企業は、短期の半導体ショックで売られた場合に積み立て的に拾う視点も有効との見方もある。ただし自分のポートフォリオ全体のリスク許容度を必ず確認すること。\n\n---\n\n## かぶぼっちコメント\n\n嵐の日に傘を持っている人は少ない。でも下げ相場で上がった銘柄を見ると、「なぜ上がったか」が見えてくる。その「なぜ」を積み重ねることが、スイングトレーダーとしての力になる。今日は損しないことより、学ぶことを優先してもいい日かもしれない。\n\n---\n\n## 明日の注目ポイント3つ\n\n1. **本日夜の米国市場（SOX・ナスダック）の反応** → 半導体の下落が継続するか底打ちするかが明日の日本株を左右する可能性がある\n2. **6月ADP全国雇用者数（米国）** → 7/10の米雇用統計の前哨戦として市場が注目する可能性あり\n3. **逆行高銘柄の継続性確認** → 本日上昇した金融・内需銘柄が2日連続で強さを維持するかどうかがセクターローテーションの本物かどうかの判断材料になる\n\n---\n\n*本記事はスイングトレードの参考情報として提供しています。投資判断はご自身の責任で行ってください。日本株・米国株・スイングトレード・日経平均・半導体・AI関連の情報を毎朝発信中です。*",
  "note_cta": "毎朝の相場分析と注目銘柄は継続発信中。フォローしてお待ちください📊"
}