{
  "date": "2026/07/17",
  "mode": "normal",
  "market_summary": "前営業日の日経225は68,751円、前々営業日比+1,008円と力強く締めた一方、昨夜のSOX指数が-4.3%と半導体セクターに冷や水を浴びせた格好だ。為替はドル円162.36円と円安水準を維持しており、輸出関連には追い風の構図が続く。VIX16.7と市場の恐怖感は落ち着いており、パニック売りというより「選別の局面」に入ってきた印象だ。今日は半導体・グロース系と輸出・ディフェンシブ系の明暗がはっきり分かれる一日になりそう、とかぶぼっちは読んでいる。",
  "nikkei": 64141,
  "nikkei_diff": -2694,
  "nikkei_pct": -4.030822174010623,
  "usd_jpy": 162.35,
  "sox_pct": -1.6314333394775646,
  "sox": 11673.9,
  "vix": 18.8,
  "topix": 4034.0,
  "topix_pct": -2.75,
  "nasdaq": 25520.2,
  "nasdaq_pct": -1.4,
  "sp500": 7457.7,
  "sp500_pct": -1.01,
  "news": [
    {
      "tag": "警戒",
      "headline": "SOX -4.3%の衝撃波、東京の半導体銘柄はどこまで飲み込まれるか",
      "body": "昨夜の米国市場でSOX指数が-4.3%と大きく崩れた。東京エレクトロンや信越化学などはすでに前営業日に下落で織り込み始めているが、今朝の寄り付きで追加の売り圧力が出るかどうかが最初の関門だ。半導体セクターへの波及リスクは過小評価しないほうがいい、というのが正直なところ。"
    },
    {
      "tag": "チャンス",
      "headline": "円安162円台が続く限り、輸出・自動車セクターの恩恵は消えない",
      "body": "ドル円162.36円という水準は、トヨタや本田技研のような自動車大手にとって業績上振れ期待を支える地合いだ。前営業日にトヨタ+1.2%、本田+3.1%と既にモメンタムが出ており、円安継続をどう見るかが今週の自動車セクター戦略の軸になりそう。ただし「円安永続」と決め込むのは禁物で、急反転リスクは常に頭に入れておきたい。"
    },
    {
      "tag": "日本",
      "headline": "日経は68,751円で高値圏、ここから上に行くか息継ぎするか",
      "body": "前々営業日比+1,008円（+1.49%）という強い上昇を経て、日経225は高値圏に位置している。ここ数営業日で一気に駆け上がった銘柄には過熱シグナルも点灯しており、三菱UFJのRSI79.5、リクルートHDのRSI75.0などは「そろそろ一息」のサインとも読める。上げ相場の中でも冷静に過熱銘柄を避ける選球眼が試されるタイミングだ。"
    },
    {
      "tag": "米国",
      "headline": "VIX16.7「まだ怖くない」、だが半導体ショックとの距離感に注意",
      "body": "VIX16.7は市場全体としては「通常モード」の域内だが、SOXの急落と共存しているのがやや複雑な絵だ。AI・半導体への集中投資が続いてきただけに、局所的な暴落が全体に波及する可能性も否定はできない。今日は「VIXが低いから安心」ではなく「セクターごとのリスク管理」を意識した立ち回りが求められる。"
    }
  ],
  "stocks_jp": [
    {
      "pattern": "モメンタム",
      "code": "7267",
      "name": "本田技研工業",
      "score": 8,
      "entry": "MA25乖離+5.6%を踏まえ、前営業日終値水準からやや押したところ（RSI70未満に落ち着いたタイミング）",
      "target": "+3%",
      "stop": "-2%",
      "reason": "前営業日+3.1%と強いモメンタムを示し、円安162円台という為替環境も追い風だ。RSI69.4はまだ買われすぎの域に入りきっておらず、上値余地が残る可能性がある。ただしBB上限に位置しており、一時的な押し目を待ってからのエントリーが相対的にリスクを抑えやすいとの見方もある。",
      "comment": "円安という名の追い風を背に走るランナー、乗るなら呼吸が整ったところで。",
      "ai_score": 48,
      "rsi": 69.4,
      "vol_ratio": 0.76
    },
    {
      "pattern": "暴落リバウンド",
      "code": "9984",
      "name": "ソフトバンクグループ",
      "score": 7,
      "entry": "RSI33.0・BB中間付近、さらにRSI30以下に接近した場面での打診買いを検討",
      "target": "+3%",
      "stop": "-2%",
      "reason": "前営業日-6.3%と大幅安となりMA25乖離が-7.3%まで拡大、RSIも33.0と売られすぎゾーンに近づいている。テクニカル的にはリバウンドの素地が整いつつあるとの見方もあるが、下落トリガーとなった材料の精査が必須だ。押し目としての魅力はあるものの、更なる売りが出るリスクも同時に存在するため、ポジションサイズは抑えめで臨みたい。",
      "comment": "-6%という傷は深い。ヒーローが復活するのはもう一段安い場面かもしれない。",
      "ai_score": 43,
      "rsi": 33.0,
      "vol_ratio": 1.0
    },
    {
      "pattern": "押し目買い",
      "code": "6861",
      "name": "キーエンス",
      "score": 7,
      "entry": "BB下限・RSI41.9付近での下げ止まり確認後、反発の初動を捉えるイメージで",
      "target": "+3%",
      "stop": "-2%",
      "reason": "前営業日-3.4%と下落し、MA25乖離-4.1%・BB下限付近と押し目圏に突入している。RSI41.9はニュートラル寄りで売られすぎとも言い切れないが、質の高いグロース銘柄が下げてきた局面は中長期目線の投資家にとって注目しやすいゾーンとの見方もある。SOXの影響を受けやすい精密機器セクターである点には引き続き注意が必要だ。",
      "comment": "高級時計が値引きされているようなもの。ただし底値かどうかは時計が止まってから分かる。",
      "ai_score": 59,
      "rsi": 41.9,
      "vol_ratio": 0.97
    },
    {
      "pattern": "イベントドリブン",
      "code": "4568",
      "name": "第一三共",
      "score": 8,
      "entry": "前営業日終値水準から極端に乖離しないタイミング、RSI70を超えない範囲でのエントリーを意識",
      "target": "+3%",
      "stop": "-2%",
      "reason": "前営業日+2.6%と強い上昇を示し、MA25乖離+4.6%・RSI67.8と勢いが続いている。医薬品セクターはSOXショックの影響を受けにくく、半導体軟調地合いでのディフェンシブな選択肢として注目しやすい構図だ。ただしBB上限接近につき、過熱感が出始めたら一旦様子見に切り替える柔軟性も持っておきたい。",
      "comment": "半導体に嵐が吹くとき、製薬の島は不思議と静かだったりする。",
      "ai_score": 47,
      "rsi": 67.8,
      "vol_ratio": 0.81
    },
    {
      "pattern": "セクターローテーション",
      "code": "9983",
      "name": "ファーストリテイリング",
      "score": 7,
      "entry": "BB下限・RSI34.2付近での底値確認、RSI30接近またはローソク足の実体的な反転サインを確認後",
      "target": "+3%",
      "stop": "-2%",
      "reason": "前営業日ほぼ横ばいながらRSI34.2・BB下限・MA25乖離-4.9%と売られた状態が続いており、テクニカル的な反発候補として浮上しやすい局面だ。内需消費セクターとして半導体ショックの直撃は受けにくく、資金の受け皿になる可能性もゼロではない。ただし直近の弱さが続いているため、反転確認なしの飛び乗りは避けたい。",
      "comment": "地面スレスレを飛ぶ飛行機、もう少し高度を保ってから乗りたいものだ。",
      "ai_score": 53,
      "rsi": 34.2,
      "vol_ratio": 1.24
    }
  ],
  "stock_us": {
    "pattern": "バフェット式",
    "ticker": "$NVDA",
    "name": "エヌビディア",
    "score": 7,
    "entry": "SOX急落後の過剰反応売りが落ち着いた水準、RSIや週足サポートを確認してから打診",
    "target": "+3%",
    "stop": "-2%",
    "reason": "SOX-4.3%の震源地はAI・半導体の牽引役であるNVDAを直撃している可能性が高く、短期的には追加の下押し圧力も考えられる。一方でAI需要の長期トレンドが崩れたとの見方は現時点では少数派であり、過度な下落は中期的な押し目との見方もある。ただし「SOX急落後の底」は確認してからでないと早すぎる可能性があるため、慎重なアプローチが求められる。",
    "comment": "AI革命の顔役が転んだとき、拾うか見守るか——それがスイングトレーダーの分かれ道。"
  },
  "consideration": {
    "main": "今日の相場を一言で表すなら「嵐の中の選別試験」だ。日経は高値圏にあるが、SOX-4.3%という黒板消しが半導体・AI関連に消しゴムをかけにきた。全部売るのも全部持つのも違う——今日のような局面こそ、影響を受けにくいセクター（医薬品・内需消費・自動車）と正面から食らうセクター（半導体製造装置・精密機器）を仕分ける腕が問われる。高RSI・BB上限の銘柄は利益確定の「出口戦略」を先に考え、低RSI・BB下限の銘柄は焦らず「確認→打診」で入る。今日は欲張らず、1〜2銘柄に絞ってシンプルに構えるのが最善だとかぶぼっちは考えている。",
    "point": "SOXショックを全部食らう前に、今日のポートフォリオを「嵐に強い銘柄」で再確認せよ。",
    "action": "保有銘柄のセクターとRSIを今すぐチェックし、RSI70超・BB上限にある銘柄の利益確定ラインを具体的に決めてから取引を始めること。"
  },
  "surges": [
    {
      "code": "9697",
      "name": "カプコン",
      "pct": 4.06,
      "price": 3412
    },
    {
      "code": "3382",
      "name": "セブン&アイHD",
      "pct": 3.64,
      "price": 2080
    },
    {
      "code": "7974",
      "name": "任天堂",
      "pct": 3.02,
      "price": 7294
    },
    {
      "code": "9101",
      "name": "日本郵船",
      "pct": 3.0,
      "price": 5706
    }
  ],
  "drops": [
    {
      "code": "3436",
      "name": "SUMCO",
      "pct": -15.17,
      "price": 3914
    },
    {
      "code": "6920",
      "name": "レーザーテック",
      "pct": -9.66,
      "price": 41890
    },
    {
      "code": "9984",
      "name": "ソフトバンクG",
      "pct": -9.01,
      "price": 5424
    },
    {
      "code": "8035",
      "name": "東京エレクトロン",
      "pct": -8.17,
      "price": 65100
    },
    {
      "code": "6723",
      "name": "ルネサスエレクトロニクス",
      "pct": -7.66,
      "price": 3822
    }
  ],
  "sector_heatmap": [
    {
      "sector": "ゲーム・娯楽",
      "avg_pct": 3.02,
      "count": 3,
      "up": 3,
      "down": 0,
      "top_mover": {
        "name": "カプコン",
        "code": "9697",
        "pct": 4.06
      }
    },
    {
      "sector": "医療機器",
      "avg_pct": 2.74,
      "count": 1,
      "up": 1,
      "down": 0,
      "top_mover": {
        "name": "テルモ",
        "code": "4543",
        "pct": 2.74
      }
    },
    {
      "sector": "医薬品",
      "avg_pct": 1.97,
      "count": 4,
      "up": 4,
      "down": 0,
      "top_mover": {
        "name": "エーザイ",
        "code": "4523",
        "pct": 2.58
      }
    },
    {
      "sector": "小売",
      "avg_pct": 1.8,
      "count": 3,
      "up": 2,
      "down": 0,
      "top_mover": {
        "name": "セブン&アイHD",
        "code": "3382",
        "pct": 3.64
      }
    },
    {
      "sector": "運輸",
      "avg_pct": 1.73,
      "count": 3,
      "up": 3,
      "down": 0,
      "top_mover": {
        "name": "日本郵船",
        "code": "9101",
        "pct": 3.0
      }
    },
    {
      "sector": "生活必需品",
      "avg_pct": 1.7,
      "count": 5,
      "up": 5,
      "down": 0,
      "top_mover": {
        "name": "JT",
        "code": "2914",
        "pct": 2.45
      }
    },
    {
      "sector": "サービス",
      "avg_pct": 0.19,
      "count": 2,
      "up": 1,
      "down": 1,
      "top_mover": {
        "name": "リクルートH",
        "code": "6098",
        "pct": 1.63
      }
    },
    {
      "sector": "自動車",
      "avg_pct": -0.23,
      "count": 5,
      "up": 2,
      "down": 3,
      "top_mover": {
        "name": "ホンダ",
        "code": "7267",
        "pct": -1.48
      }
    },
    {
      "sector": "精密機器",
      "avg_pct": -1.44,
      "count": 2,
      "up": 1,
      "down": 1,
      "top_mover": {
        "name": "キーエンス",
        "code": "6861",
        "pct": -4.28
      }
    },
    {
      "sector": "通信・IT",
      "avg_pct": -1.49,
      "count": 6,
      "up": 3,
      "down": 3,
      "top_mover": {
        "name": "ソフトバンクG",
        "code": "9984",
        "pct": -9.01
      }
    },
    {
      "sector": "不動産",
      "avg_pct": -1.6,
      "count": 2,
      "up": 0,
      "down": 2,
      "top_mover": {
        "name": "三菱地所",
        "code": "8802",
        "pct": -2.44
      }
    },
    {
      "sector": "エネルギー",
      "avg_pct": -1.6,
      "count": 2,
      "up": 0,
      "down": 2,
      "top_mover": {
        "name": "ENEOSホールディングス",
        "code": "5020",
        "pct": -2.39
      }
    },
    {
      "sector": "電機",
      "avg_pct": -1.68,
      "count": 6,
      "up": 3,
      "down": 3,
      "top_mover": {
        "name": "パナソニックHD",
        "code": "6752",
        "pct": -5.33
      }
    },
    {
      "sector": "素材",
      "avg_pct": -1.8,
      "count": 4,
      "up": 1,
      "down": 3,
      "top_mover": {
        "name": "三菱ケミカルG",
        "code": "4188",
        "pct": -2.87
      }
    },
    {
      "sector": "商社",
      "avg_pct": -2.17,
      "count": 4,
      "up": 0,
      "down": 4,
      "top_mover": {
        "name": "住友商事",
        "code": "8053",
        "pct": -4.36
      }
    },
    {
      "sector": "機械",
      "avg_pct": -3.9,
      "count": 4,
      "up": 0,
      "down": 4,
      "top_mover": {
        "name": "SMC",
        "code": "6273",
        "pct": -5.72
      }
    },
    {
      "sector": "建設",
      "avg_pct": -4.06,
      "count": 1,
      "up": 0,
      "down": 1,
      "top_mover": {
        "name": "大成建設",
        "code": "1801",
        "pct": -4.06
      }
    },
    {
      "sector": "金融",
      "avg_pct": -4.25,
      "count": 5,
      "up": 0,
      "down": 5,
      "top_mover": {
        "name": "みずほFG",
        "code": "8411",
        "pct": -6.04
      }
    },
    {
      "sector": "半導体",
      "avg_pct": -9.57,
      "count": 5,
      "up": 0,
      "down": 5,
      "top_mover": {
        "name": "SUMCO",
        "code": "3436",
        "pct": -15.17
      }
    }
  ],
  "jp_top_movers": [
    {
      "code": "3436",
      "name": "SUMCO",
      "pct": -15.17,
      "price": 3914,
      "sector": "半導体"
    },
    {
      "code": "6920",
      "name": "レーザーテック",
      "pct": -9.66,
      "price": 41890,
      "sector": "半導体"
    },
    {
      "code": "9984",
      "name": "ソフトバンクG",
      "pct": -9.01,
      "price": 5424,
      "sector": "通信・IT"
    },
    {
      "code": "8035",
      "name": "東京エレクトロン",
      "pct": -8.17,
      "price": 65100,
      "sector": "半導体"
    },
    {
      "code": "6723",
      "name": "ルネサスエレクトロニクス",
      "pct": -7.66,
      "price": 3822,
      "sector": "半導体"
    },
    {
      "code": "6857",
      "name": "アドバンテスト",
      "pct": -7.2,
      "price": 27505,
      "sector": "半導体"
    },
    {
      "code": "8411",
      "name": "みずほFG",
      "pct": -6.04,
      "price": 7930,
      "sector": "金融"
    },
    {
      "code": "6273",
      "name": "SMC",
      "pct": -5.72,
      "price": 69230,
      "sector": "機械"
    },
    {
      "code": "8604",
      "name": "野村HD",
      "pct": -5.53,
      "price": 1520,
      "sector": "金融"
    },
    {
      "code": "6954",
      "name": "ファナック",
      "pct": -5.46,
      "price": 6637,
      "sector": "機械"
    }
  ],
  "jp_all_changes": [
    {
      "code": "7203",
      "name": "トヨタ自動車",
      "pct": -0.33,
      "price": 2899,
      "sector": "自動車"
    },
    {
      "code": "9984",
      "name": "ソフトバンクG",
      "pct": -9.01,
      "price": 5424,
      "sector": "通信・IT"
    },
    {
      "code": "6758",
      "name": "ソニーG",
      "pct": 0.93,
      "price": 3470,
      "sector": "電機"
    },
    {
      "code": "6861",
      "name": "キーエンス",
      "pct": -4.28,
      "price": 70880,
      "sector": "精密機器"
    },
    {
      "code": "8306",
      "name": "三菱UFJ",
      "pct": -4.3,
      "price": 3473,
      "sector": "金融"
    },
    {
      "code": "9432",
      "name": "NTT",
      "pct": 0.13,
      "price": 151,
      "sector": "通信・IT"
    },
    {
      "code": "4063",
      "name": "信越化学",
      "pct": -2.77,
      "price": 7157,
      "sector": "素材"
    },
    {
      "code": "6954",
      "name": "ファナック",
      "pct": -5.46,
      "price": 6637,
      "sector": "機械"
    },
    {
      "code": "8035",
      "name": "東京エレクトロン",
      "pct": -8.17,
      "price": 65100,
      "sector": "半導体"
    },
    {
      "code": "6367",
      "name": "ダイキン工業",
      "pct": -1.49,
      "price": 24500,
      "sector": "機械"
    },
    {
      "code": "8058",
      "name": "三菱商事",
      "pct": -1.83,
      "price": 4447,
      "sector": "商社"
    },
    {
      "code": "6098",
      "name": "リクルートH",
      "pct": 1.63,
      "price": 12820,
      "sector": "サービス"
    },
    {
      "code": "7974",
      "name": "任天堂",
      "pct": 3.02,
      "price": 7294,
      "sector": "ゲーム・娯楽"
    },
    {
      "code": "4568",
      "name": "第一三共",
      "pct": 1.62,
      "price": 2791,
      "sector": "医薬品"
    },
    {
      "code": "9983",
      "name": "ファーストリテイリング",
      "pct": 0.0,
      "price": 78840,
      "sector": "小売"
    },
    {
      "code": "6501",
      "name": "日立製作所",
      "pct": -2.3,
      "price": 4717,
      "sector": "電機"
    },
    {
      "code": "7267",
      "name": "ホンダ",
      "pct": -1.48,
      "price": 1535,
      "sector": "自動車"
    },
    {
      "code": "2914",
      "name": "JT",
      "pct": 2.45,
      "price": 6347,
      "sector": "生活必需品"
    },
    {
      "code": "4543",
      "name": "テルモ",
      "pct": 2.74,
      "price": 2267,
      "sector": "医療機器"
    },
    {
      "code": "4519",
      "name": "中外製薬",
      "pct": 1.16,
      "price": 7325,
      "sector": "医薬品"
    },
    {
      "code": "6857",
      "name": "アドバンテスト",
      "pct": -7.2,
      "price": 27505,
      "sector": "半導体"
    },
    {
      "code": "6920",
      "name": "レーザーテック",
      "pct": -9.66,
      "price": 41890,
      "sector": "半導体"
    },
    {
      "code": "4452",
      "name": "花王",
      "pct": 0.7,
      "price": 3308,
      "sector": "生活必需品"
    },
    {
      "code": "9433",
      "name": "KDDI",
      "pct": 0.84,
      "price": 2868,
      "sector": "通信・IT"
    },
    {
      "code": "8316",
      "name": "三井住友FG",
      "pct": -4.4,
      "price": 6721,
      "sector": "金融"
    },
    {
      "code": "7751",
      "name": "キヤノン",
      "pct": 1.57,
      "price": 4466,
      "sector": "電機"
    },
    {
      "code": "4901",
      "name": "富士フイルム",
      "pct": 0.25,
      "price": 3633,
      "sector": "電機"
    },
    {
      "code": "6702",
      "name": "富士通",
      "pct": 1.26,
      "price": 3298,
      "sector": "通信・IT"
    },
    {
      "code": "9022",
      "name": "東海旅客鉄道",
      "pct": 1.54,
      "price": 3766,
      "sector": "運輸"
    },
    {
      "code": "8802",
      "name": "三菱地所",
      "pct": -2.44,
      "price": 4112,
      "sector": "不動産"
    },
    {
      "code": "7201",
      "name": "日産自動車",
      "pct": 0.09,
      "price": 329,
      "sector": "自動車"
    },
    {
      "code": "7269",
      "name": "スズキ",
      "pct": -0.07,
      "price": 2050,
      "sector": "自動車"
    },
    {
      "code": "7270",
      "name": "SUBARU",
      "pct": 0.62,
      "price": 2534,
      "sector": "自動車"
    },
    {
      "code": "4689",
      "name": "LINEヤフー",
      "pct": -1.67,
      "price": 447,
      "sector": "通信・IT"
    },
    {
      "code": "4307",
      "name": "野村総合研究所",
      "pct": -0.47,
      "price": 5076,
      "sector": "通信・IT"
    },
    {
      "code": "6503",
      "name": "三菱電機",
      "pct": -5.22,
      "price": 5370,
      "sector": "電機"
    },
    {
      "code": "6752",
      "name": "パナソニックHD",
      "pct": -5.33,
      "price": 3993,
      "sector": "電機"
    },
    {
      "code": "7733",
      "name": "オリンパス",
      "pct": 1.4,
      "price": 1771,
      "sector": "精密機器"
    },
    {
      "code": "8411",
      "name": "みずほFG",
      "pct": -6.04,
      "price": 7930,
      "sector": "金融"
    },
    {
      "code": "8604",
      "name": "野村HD",
      "pct": -5.53,
      "price": 1520,
      "sector": "金融"
    },
    {
      "code": "8766",
      "name": "東京海上HD",
      "pct": -0.97,
      "price": 7526,
      "sector": "金融"
    },
    {
      "code": "5401",
      "name": "日本製鉄",
      "pct": 0.93,
      "price": 585,
      "sector": "素材"
    },
    {
      "code": "4188",
      "name": "三菱ケミカルG",
      "pct": -2.87,
      "price": 1168,
      "sector": "素材"
    },
    {
      "code": "3407",
      "name": "旭化成",
      "pct": -2.48,
      "price": 1829,
      "sector": "素材"
    },
    {
      "code": "6301",
      "name": "コマツ",
      "pct": -2.93,
      "price": 6251,
      "sector": "機械"
    },
    {
      "code": "6273",
      "name": "SMC",
      "pct": -5.72,
      "price": 69230,
      "sector": "機械"
    },
    {
      "code": "6723",
      "name": "ルネサスエレクトロニクス",
      "pct": -7.66,
      "price": 3822,
      "sector": "半導体"
    },
    {
      "code": "3436",
      "name": "SUMCO",
      "pct": -15.17,
      "price": 3914,
      "sector": "半導体"
    },
    {
      "code": "8031",
      "name": "三井物産",
      "pct": -1.6,
      "price": 4662,
      "sector": "商社"
    },
    {
      "code": "8001",
      "name": "伊藤忠商事",
      "pct": -0.89,
      "price": 1902,
      "sector": "商社"
    },
    {
      "code": "8053",
      "name": "住友商事",
      "pct": -4.36,
      "price": 1514,
      "sector": "商社"
    },
    {
      "code": "4755",
      "name": "楽天G",
      "pct": -1.25,
      "price": 799,
      "sector": "サービス"
    },
    {
      "code": "9697",
      "name": "カプコン",
      "pct": 4.06,
      "price": 3412,
      "sector": "ゲーム・娯楽"
    },
    {
      "code": "7832",
      "name": "バンダイナムコHD",
      "pct": 1.97,
      "price": 4189,
      "sector": "ゲーム・娯楽"
    },
    {
      "code": "4502",
      "name": "武田薬品工業",
      "pct": 2.53,
      "price": 5480,
      "sector": "医薬品"
    },
    {
      "code": "4523",
      "name": "エーザイ",
      "pct": 2.58,
      "price": 4450,
      "sector": "医薬品"
    },
    {
      "code": "3382",
      "name": "セブン&アイHD",
      "pct": 3.64,
      "price": 2080,
      "sector": "小売"
    },
    {
      "code": "8267",
      "name": "イオン",
      "pct": 1.75,
      "price": 1395,
      "sector": "小売"
    },
    {
      "code": "2502",
      "name": "アサヒグループHD",
      "pct": 1.26,
      "price": 1603,
      "sector": "生活必需品"
    },
    {
      "code": "2503",
      "name": "キリンHD",
      "pct": 1.93,
      "price": 2909,
      "sector": "生活必需品"
    },
    {
      "code": "2801",
      "name": "キッコーマン",
      "pct": 2.14,
      "price": 1667,
      "sector": "生活必需品"
    },
    {
      "code": "9020",
      "name": "東日本旅客鉄道",
      "pct": 0.64,
      "price": 3624,
      "sector": "運輸"
    },
    {
      "code": "9101",
      "name": "日本郵船",
      "pct": 3.0,
      "price": 5706,
      "sector": "運輸"
    },
    {
      "code": "8801",
      "name": "三井不動産",
      "pct": -0.77,
      "price": 1537,
      "sector": "不動産"
    },
    {
      "code": "5020",
      "name": "ENEOSホールディングス",
      "pct": -2.39,
      "price": 1243,
      "sector": "エネルギー"
    },
    {
      "code": "1605",
      "name": "INPEX",
      "pct": -0.82,
      "price": 3401,
      "sector": "エネルギー"
    },
    {
      "code": "1801",
      "name": "大成建設",
      "pct": -4.06,
      "price": 13340,
      "sector": "建設"
    }
  ],
  "us_sector_heatmap": [
    {
      "sector": "エネルギー",
      "avg_pct": 1.44,
      "count": 2,
      "up": 2,
      "down": 0,
      "top_mover": {
        "name": "Chevron",
        "code": "CVX",
        "pct": 1.91
      }
    },
    {
      "sector": "ヘルスケア",
      "avg_pct": 0.91,
      "count": 3,
      "up": 3,
      "down": 0,
      "top_mover": {
        "name": "Johnson & Johnson",
        "code": "JNJ",
        "pct": 1.23
      }
    },
    {
      "sector": "資本財",
      "avg_pct": 0.37,
      "count": 3,
      "up": 2,
      "down": 1,
      "top_mover": {
        "name": "GE Aerospace",
        "code": "GE",
        "pct": 0.9
      }
    },
    {
      "sector": "金融",
      "avg_pct": -1.24,
      "count": 3,
      "up": 0,
      "down": 3,
      "top_mover": {
        "name": "Goldman Sachs",
        "code": "GS",
        "pct": -2.76
      }
    },
    {
      "sector": "テクノロジー",
      "avg_pct": -1.28,
      "count": 3,
      "up": 1,
      "down": 2,
      "top_mover": {
        "name": "Alphabet",
        "code": "GOOGL",
        "pct": -2.17
      }
    },
    {
      "sector": "半導体",
      "avg_pct": -1.4,
      "count": 3,
      "up": 0,
      "down": 3,
      "top_mover": {
        "name": "NVIDIA",
        "code": "NVDA",
        "pct": -2.21
      }
    },
    {
      "sector": "消費・EC",
      "avg_pct": -1.43,
      "count": 3,
      "up": 0,
      "down": 3,
      "top_mover": {
        "name": "Tesla",
        "code": "TSLA",
        "pct": -2.61
      }
    },
    {
      "sector": "生活必需品",
      "avg_pct": -1.82,
      "count": 3,
      "up": 0,
      "down": 3,
      "top_mover": {
        "name": "Coca-Cola",
        "code": "KO",
        "pct": -3.96
      }
    },
    {
      "sector": "通信・メディア",
      "avg_pct": -4.03,
      "count": 3,
      "up": 0,
      "down": 3,
      "top_mover": {
        "name": "Netflix",
        "code": "NFLX",
        "pct": -7.26
      }
    }
  ],
  "us_top_movers": [
    {
      "code": "NFLX",
      "name": "Netflix",
      "pct": -7.26,
      "price": 68.95,
      "sector": "通信・メディア"
    },
    {
      "code": "KO",
      "name": "Coca-Cola",
      "pct": -3.96,
      "price": 81.56,
      "sector": "生活必需品"
    },
    {
      "code": "META",
      "name": "Meta Platforms",
      "pct": -2.79,
      "price": 646.01,
      "sector": "通信・メディア"
    },
    {
      "code": "GS",
      "name": "Goldman Sachs",
      "pct": -2.76,
      "price": 1065.22,
      "sector": "金融"
    },
    {
      "code": "TSLA",
      "name": "Tesla",
      "pct": -2.61,
      "price": 380.84,
      "sector": "消費・EC"
    },
    {
      "code": "NVDA",
      "name": "NVIDIA",
      "pct": -2.21,
      "price": 202.81,
      "sector": "半導体"
    },
    {
      "code": "GOOGL",
      "name": "Alphabet",
      "pct": -2.17,
      "price": 346.77,
      "sector": "テクノロジー"
    },
    {
      "code": "DIS",
      "name": "Disney",
      "pct": -2.05,
      "price": 97.67,
      "sector": "通信・メディア"
    },
    {
      "code": "CVX",
      "name": "Chevron",
      "pct": 1.91,
      "price": 187.38,
      "sector": "エネルギー"
    },
    {
      "code": "MSFT",
      "name": "Microsoft",
      "pct": -1.82,
      "price": 393.82,
      "sector": "テクノロジー"
    }
  ],
  "us_all_changes": [
    {
      "code": "AAPL",
      "name": "Apple",
      "pct": 0.14,
      "price": 333.74,
      "sector": "テクノロジー"
    },
    {
      "code": "MSFT",
      "name": "Microsoft",
      "pct": -1.82,
      "price": 393.82,
      "sector": "テクノロジー"
    },
    {
      "code": "GOOGL",
      "name": "Alphabet",
      "pct": -2.17,
      "price": 346.77,
      "sector": "テクノロジー"
    },
    {
      "code": "NVDA",
      "name": "NVIDIA",
      "pct": -2.21,
      "price": 202.81,
      "sector": "半導体"
    },
    {
      "code": "AMD",
      "name": "AMD",
      "pct": -1.03,
      "price": 495.76,
      "sector": "半導体"
    },
    {
      "code": "AVGO",
      "name": "Broadcom",
      "pct": -0.97,
      "price": 370.83,
      "sector": "半導体"
    },
    {
      "code": "AMZN",
      "name": "Amazon",
      "pct": -1.06,
      "price": 247.23,
      "sector": "消費・EC"
    },
    {
      "code": "TSLA",
      "name": "Tesla",
      "pct": -2.61,
      "price": 380.84,
      "sector": "消費・EC"
    },
    {
      "code": "WMT",
      "name": "Walmart",
      "pct": -0.62,
      "price": 114.24,
      "sector": "消費・EC"
    },
    {
      "code": "META",
      "name": "Meta Platforms",
      "pct": -2.79,
      "price": 646.01,
      "sector": "通信・メディア"
    },
    {
      "code": "NFLX",
      "name": "Netflix",
      "pct": -7.26,
      "price": 68.95,
      "sector": "通信・メディア"
    },
    {
      "code": "DIS",
      "name": "Disney",
      "pct": -2.05,
      "price": 97.67,
      "sector": "通信・メディア"
    },
    {
      "code": "JPM",
      "name": "JPMorgan Chase",
      "pct": -0.6,
      "price": 341.1,
      "sector": "金融"
    },
    {
      "code": "BAC",
      "name": "Bank of America",
      "pct": -0.36,
      "price": 61.27,
      "sector": "金融"
    },
    {
      "code": "GS",
      "name": "Goldman Sachs",
      "pct": -2.76,
      "price": 1065.22,
      "sector": "金融"
    },
    {
      "code": "JNJ",
      "name": "Johnson & Johnson",
      "pct": 1.23,
      "price": 253.04,
      "sector": "ヘルスケア"
    },
    {
      "code": "UNH",
      "name": "UnitedHealth",
      "pct": 0.64,
      "price": 426.09,
      "sector": "ヘルスケア"
    },
    {
      "code": "LLY",
      "name": "Eli Lilly",
      "pct": 0.85,
      "price": 1179.11,
      "sector": "ヘルスケア"
    },
    {
      "code": "XOM",
      "name": "ExxonMobil",
      "pct": 0.97,
      "price": 147.36,
      "sector": "エネルギー"
    },
    {
      "code": "CVX",
      "name": "Chevron",
      "pct": 1.91,
      "price": 187.38,
      "sector": "エネルギー"
    },
    {
      "code": "KO",
      "name": "Coca-Cola",
      "pct": -3.96,
      "price": 81.56,
      "sector": "生活必需品"
    },
    {
      "code": "PG",
      "name": "Procter & Gamble",
      "pct": -1.0,
      "price": 149.98,
      "sector": "生活必需品"
    },
    {
      "code": "COST",
      "name": "Costco",
      "pct": -0.5,
      "price": 940.87,
      "sector": "生活必需品"
    },
    {
      "code": "BA",
      "name": "Boeing",
      "pct": -0.14,
      "price": 214.03,
      "sector": "資本財"
    },
    {
      "code": "CAT",
      "name": "Caterpillar",
      "pct": 0.35,
      "price": 880.28,
      "sector": "資本財"
    },
    {
      "code": "GE",
      "name": "GE Aerospace",
      "pct": 0.9,
      "price": 348.83,
      "sector": "資本財"
    }
  ],
  "events_jp": [
    {
      "date": "2026-07-17",
      "text": "東京証券取引所 通常取引（7月第3金曜日）",
      "importance": "medium",
      "urgent": false
    },
    {
      "date": "2026-07-22",
      "text": "日銀金融政策決定会合（7月会合）結果公表・展望レポート発表予定",
      "importance": "high",
      "urgent": true
    },
    {
      "date": "2026-07-17",
      "text": "国内主要企業の1Q決算発表シーズン本格化（各社スケジュール要確認）",
      "importance": "medium",
      "urgent": false
    }
  ],
  "events_us": [
    {
      "date": "2026-07-17",
      "text": "米国 ミシガン大学消費者信頼感指数（7月速報値）発表予定",
      "importance": "medium",
      "urgent": false
    },
    {
      "date": "2026-07-28",
      "text": "FOMC（7月会合）金融政策発表・パウエル議長記者会見",
      "importance": "high",
      "urgent": true
    },
    {
      "date": "2026-07-17",
      "text": "米国主要企業決算発表（テック系・金融系を中心に続く）",
      "importance": "medium",
      "urgent": false
    }
  ],
  "x_posts": [
    "日経68,751円で高値圏にいる一方、昨夜のSOXが-4.3%と半導体に赤信号。円安162円台は輸出系の味方だけど、今日は「全部上がる日」じゃなく「どれが生き残るかを選ぶ日」だとかぶぼっちは感じてる。みんなは今日の地合いをどう読んでる？",
    "今朝かぶぼっちが一番気にしてるのはソフトバンクG(9984)の-6.3%という前日の大幅下落。RSI33.0・MA25乖離-7.3%まで売られてきたのは事実で、リバウンドの素地は出つつある。でも「安いから買う」じゃなく「なぜ売られたか」を先に確認しないと怪我する。下げた理由、ちゃんと調べた上でエントリー検討してる？",
    "突然ですが質問。SOX-4.3%の翌朝、あなたはどう動く？\nA. 半導体関連を損切りして現金確保\nB. 押し目と判断して打診買い\nC. 様子見して前場終わりに判断\nD. ノーポジで相場を観察\nかぶぼっちは正直Cとdの間で揺れてる。コメントで教えてほしい！"
  ],
  "note_body": "# 【2026/7/17 朝の相場分析】SOXショックと円安の間で、今日の日本株はどちらを向く？\n\n## ▶ 今日の相場を一言で\n「半導体という名の嵐と、円安という名の順風が同時に吹いている朝」\n\n---\n\n## 📊 今日の相場ポイント\n\n前営業日の日経225は68,751円、前々営業日比+1,008円（+1.49%）という力強い上昇で終えた。高値圏に位置する日経平均だが、今朝の最大のリスク要因は昨夜の米国市場でのSOX指数-4.3%という急落だ。\n\n半導体セクターへのネガティブな波及は避けられない可能性が高く、東京エレクトロン(8035)や信越化学(4063)、キーエンス(6861)といった銘柄への売り圧力が寄り付きに出るかどうかが最初の確認ポイントになる。前営業日にこれらの銘柄はすでにそれぞれ-4.5%・-4.3%・-3.4%と下げており、「先取り」して折り込んでいた面もあるが、追撃の売りが出るリスクは排除できない。\n\nAI・半導体という日本株市場の主役が揺れるとき、資金はどこへ向かうか。その答えの一つが「ディフェンシブ」であり、前営業日に第一三共(4568)+2.6%、中外製薬(4519)+1.6%という医薬品セクターの強さはそれを先読みしていた可能性もある。\n\n一方で円安は現在ドル円162.36円と高水準を維持しており、トヨタ自動車(7203)+1.2%・本田技研工業(7267)+3.1%と自動車セクターは輸出恩恵をはっきり数字に反映させている。半導体が下がるなかで、スイングトレードの観点から「円安恩恵銘柄」か「ディフェンシブ医薬品」をどう組み合わせるかが今日の戦略の軸だとかぶぼっちは見ている。\n\nVIX16.7はまだ「通常モード」の域内だが、SOXのセクター的な急落と組み合わせると「局所的な高ボラティリティ」が存在する複雑な相場環境だ。全部売りも全部買いも正解ではなく、銘柄選別が問われる一日になる可能性が高い。\n\n---\n\n## 🔍 注目銘柄ピックアップ\n\n### ★★★★ 第一三共（4568）｜モメンタム×ディフェンシブ\n**注目理由：** 前営業日+2.6%・MA25乖離+4.6%・RSI67.8と強いモメンタムを維持。半導体ショックの直撃を受けにくい医薬品セクターという点でも、今日の地合いに適合しやすい。\n**エントリー条件：** 前営業日終値水準から極端に乖離しないタイミング、RSIが70を超えない範囲での打診。\n**利確：** +3%程度を目安に分割で。\n**損切：** -2%を基準に、BB上限を大きく割り込んだ場面で速やかに。\n**注意点：** BB上限に接近しており、過熱感が出たら一旦引く判断を先に持っておくこと。\n\n---\n\n### ★★★★ 本田技研工業（7267）｜円安モメンタム\n**注目理由：** 前営業日+3.1%と強烈なモメンタムを示し、ドル円162円台の円安恩恵が直接的に業績期待に直結しやすい構図。RSI69.4はまだ買われすぎ圏に達していない。\n**エントリー条件：** 現値から一時的に押した場面、RSIが70未満で落ち着いたタイミングを狙う。\n**利確：** +3%を目標に、BB上限到達で一部確定。\n**損切：** -2%ライン厳守。円高急反転が起きた場合は素早く撤退。\n**注意点：** BB上限に位置しており、追いかけてのエントリーは乖離リスクがある。押し目を待つ忍耐が肝。\n\n---\n\n### ★★★ キーエンス（6861）｜押し目候補\n**注目理由：** 前営業日-3.4%・MA25乖離-4.1%・BB下限付近と売られ過ぎゾーンに差し掛かっている。質の高いグロース銘柄が一時的に崩れた局面は中長期的な押し目になる可能性がある。\n**エントリー条件：** BB下限付近での下げ止まり確認後、反発の初動が出てから打診。焦ってはいけない。\n**利確：** +3%を目安に、MA25回復が一つの目標ライン。\n**損切：** -2%で機械的に切る。SOX動向次第でさらなる下落リスクもある。\n**注意点：** 半導体・製造装置の影響を受けやすいセクターであり、SOXの余波次第では下落が続く可能性も否定できない。\n\n---\n\n### ★★★ ソフトバンクグループ（9984）｜暴落リバウンド候補\n**注目理由：** 前営業日-6.3%という大幅下落でMA25乖離-7.3%・RSI33.0まで売られた。テクニカル的にはリバウンドの条件が整いつつあるとの見方もある。\n**エントリー条件：** RSI30以下への接近・さらなる下落後の陽線確認を待ってから小ロットで打診。\n**利確：** +3%を目安に分割確定。\n**損切：** -2%で撤退。下げの材料が解消されていない場合はノータッチも選択肢。\n**注意点：** なぜ-6.3%下落したのかの材料確認が最優先。「安いから買う」は禁物。\n\n---\n\n### ★★★ ファーストリテイリング（9983）｜セクターローテーション候補\n**注目理由：** RSI34.2・BB下限・MA25乖離-4.9%と売られた状態が続いており、内需消費セクターとして半導体ショックから距離を置けるポジションにある。\n**エントリー条件：** RSI30接近または反転の明確なサイン（陽線の実体など）を確認後の打診。\n**利確：** +3%を目標に、MA25回復を一つのマイルストーンとして意識。\n**損切：** -2%厳守。反転確認前の飛び乗りは避けること。\n**注意点：** 直近の弱さが続いているため、底値を掴みに行く「逆張り」である意識を忘れずに。\n\n---\n\n## 📋 今日の売買戦略\n\n**デイトレ：** SOX急落の影響が前場でどこまで出るかを見極める時間と割り切り、前場は動きを観察・後場から動くタイムマネジメントも有効。半導体系は追いかけ厳禁。\n\n**スイングトレード：** 押し目圏に入ったキーエンス・ファーストリテイリング・ソフトバンクGを「確認→小ロット打診」で構え、反転が明確になった段階でポジションを積み上げる2段構えを意識する。\n\n**中長期：** 円安継続と医薬品の堅調という2つのテーマは引き続き有効な可能性がある。第一三共・本田技研への分散保有という観点では、今週の押し目は仕込みの機会になり得るとの見方もある。ただし為替の急変・政策変更には常に注意が必要だ。\n\n---\n\n## 💬 かぶぼっちコメント\n\n正直に言うと、SOX-4.3%を見た瞬間「今日は難しい日だな」と思った。でも難しい日こそ、銘柄を「選ぶ眼」が磨かれる。全部買い・全部売りじゃなく、「今日のテーマに合う銘柄を1〜2本に絞る」——それだけで随分ストレスが減るし、精度も上がる。焦らなくていい。相場は明日も明後日もある。\n\n---\n\n## 🔭 明日以降の注目ポイント3つ\n\n1. **SOXの反発・続落どちらか：** 今夜の米国市場でSOXが回復するか続落するかが来週の日本の半導体・製造装置セクターの方向性を左右する最重要確認ポイント。\n\n2. **ドル円162円台の持続性：** 円安が続けば自動車セクターの恩恵が続くが、日銀の政策観測（7月会合に向けた発言等）で急激な円高転換が起きるリスクには要注意。\n\n3. **医薬品セクターへの資金流入が本物か：** 第一三共・中外製薬の強さが「一時的な避難」なのか「本格的なセクターローテーション」なのかを来週前半の動きで判断したい。",
  "note_cta": "毎朝の相場分析と注目銘柄は継続発信中。フォローしてお待ちください📊",
  "usd_jpy_pct": -0.02,
  "market_data_refreshed_at": "2026-07-20T05:46:02.971577+09:00",
  "vix_pct": 12.37,
  "us10y": 4.54,
  "us10y_diff": -0.03,
  "fear_greed_value": 37.1,
  "fear_greed_label": "fear",
  "jp_earnings_calendar": [
    {
      "code": "4063",
      "name": "信越化学",
      "sector": "素材",
      "next_earnings_date": "2026-07-24",
      "days_until": 7,
      "last_earnings_date": "2026-04-28",
      "last_surprise_pct": -10.9
    },
    {
      "code": "4519",
      "name": "中外製薬",
      "sector": "医薬品",
      "next_earnings_date": "2026-07-24",
      "days_until": 7,
      "last_earnings_date": "2026-04-24",
      "last_surprise_pct": 2.2
    },
    {
      "code": "2502",
      "name": "アサヒグループHD",
      "sector": "生活必需品",
      "next_earnings_date": "2026-07-24",
      "days_until": 7,
      "last_earnings_date": "2026-07-08",
      "last_surprise_pct": -40.7
    },
    {
      "code": "7751",
      "name": "キヤノン",
      "sector": "電機",
      "next_earnings_date": "2026-07-27",
      "days_until": 10,
      "last_earnings_date": "2026-04-23",
      "last_surprise_pct": -27.9
    },
    {
      "code": "6861",
      "name": "キーエンス",
      "sector": "精密機器",
      "next_earnings_date": "2026-07-28",
      "days_until": 11,
      "last_earnings_date": "2026-04-24",
      "last_surprise_pct": 16.8
    },
    {
      "code": "9697",
      "name": "カプコン",
      "sector": "ゲーム・娯楽",
      "next_earnings_date": "2026-07-28",
      "days_until": 11,
      "last_earnings_date": "2026-05-13",
      "last_surprise_pct": -14.7
    },
    {
      "code": "6501",
      "name": "日立製作所",
      "sector": "電機",
      "next_earnings_date": "2026-07-29",
      "days_until": 12,
      "last_earnings_date": "2026-04-27",
      "last_surprise_pct": -3.4
    },
    {
      "code": "6857",
      "name": "アドバンテスト",
      "sector": "半導体",
      "next_earnings_date": "2026-07-29",
      "days_until": 12,
      "last_earnings_date": "2026-04-27",
      "last_surprise_pct": 27.5
    },
    {
      "code": "8604",
      "name": "野村HD",
      "sector": "金融",
      "next_earnings_date": "2026-07-29",
      "days_until": 12,
      "last_earnings_date": "2026-04-24",
      "last_surprise_pct": -28.7
    },
    {
      "code": "6301",
      "name": "コマツ",
      "sector": "機械",
      "next_earnings_date": "2026-07-29",
      "days_until": 12,
      "last_earnings_date": "2026-04-28",
      "last_surprise_pct": 7.8
    },
    {
      "code": "8035",
      "name": "東京エレクトロン",
      "sector": "半導体",
      "next_earnings_date": "2026-07-30",
      "days_until": 13,
      "last_earnings_date": "2026-04-30",
      "last_surprise_pct": 14.6
    },
    {
      "code": "2914",
      "name": "JT",
      "sector": "生活必需品",
      "next_earnings_date": "2026-07-30",
      "days_until": 13,
      "last_earnings_date": "2026-05-08",
      "last_surprise_pct": 15.6
    },
    {
      "code": "6702",
      "name": "富士通",
      "sector": "通信・IT",
      "next_earnings_date": "2026-07-30",
      "days_until": 13,
      "last_earnings_date": "2026-04-28",
      "last_surprise_pct": -18.1
    },
    {
      "code": "4307",
      "name": "野村総合研究所",
      "sector": "通信・IT",
      "next_earnings_date": "2026-07-30",
      "days_until": 13,
      "last_earnings_date": "2026-04-24",
      "last_surprise_pct": -449.9
    },
    {
      "code": "6752",
      "name": "パナソニックHD",
      "sector": "電機",
      "next_earnings_date": "2026-07-30",
      "days_until": 13,
      "last_earnings_date": "2026-05-12",
      "last_surprise_pct": -34.9
    }
  ],
  "jp_earnings_rank": {
    "best": [
      {
        "code": "5401",
        "name": "日本製鉄",
        "sector": "素材",
        "next_earnings_date": "2026-08-04",
        "days_until": 18,
        "last_earnings_date": "2026-05-13",
        "last_surprise_pct": 3561.0
      },
      {
        "code": "9984",
        "name": "ソフトバンクG",
        "sector": "通信・IT",
        "next_earnings_date": "2026-08-06",
        "days_until": 20,
        "last_earnings_date": "2026-05-13",
        "last_surprise_pct": 491.3
      },
      {
        "code": "5020",
        "name": "ENEOSホールディングス",
        "sector": "エネルギー",
        "next_earnings_date": "2026-08-07",
        "days_until": 21,
        "last_earnings_date": "2026-05-14",
        "last_surprise_pct": 161.6
      },
      {
        "code": "7733",
        "name": "オリンパス",
        "sector": "精密機器",
        "next_earnings_date": "2026-08-07",
        "days_until": 21,
        "last_earnings_date": "2026-05-12",
        "last_surprise_pct": 143.9
      },
      {
        "code": "3382",
        "name": "セブン&アイHD",
        "sector": "小売",
        "next_earnings_date": "2026-10-08",
        "days_until": 83,
        "last_earnings_date": "2026-07-09",
        "last_surprise_pct": 115.4
      },
      {
        "code": "8267",
        "name": "イオン",
        "sector": "小売",
        "next_earnings_date": "2026-10-08",
        "days_until": 83,
        "last_earnings_date": "2026-07-10",
        "last_surprise_pct": 72.7
      },
      {
        "code": "8766",
        "name": "東京海上HD",
        "sector": "金融",
        "next_earnings_date": "2026-08-12",
        "days_until": 26,
        "last_earnings_date": "2024-02-14",
        "last_surprise_pct": 72.1
      },
      {
        "code": "4755",
        "name": "楽天G",
        "sector": "サービス",
        "next_earnings_date": "2026-08-10",
        "days_until": 24,
        "last_earnings_date": "2026-05-14",
        "last_surprise_pct": 51.1
      },
      {
        "code": "9022",
        "name": "東海旅客鉄道",
        "sector": "運輸",
        "next_earnings_date": "2026-07-31",
        "days_until": 14,
        "last_earnings_date": "2026-04-28",
        "last_surprise_pct": 45.6
      },
      {
        "code": "8306",
        "name": "三菱UFJ",
        "sector": "金融",
        "next_earnings_date": "2026-08-03",
        "days_until": 17,
        "last_earnings_date": "2026-05-15",
        "last_surprise_pct": 41.1
      }
    ],
    "worst": [
      {
        "code": "4307",
        "name": "野村総合研究所",
        "sector": "通信・IT",
        "next_earnings_date": "2026-07-30",
        "days_until": 13,
        "last_earnings_date": "2026-04-24",
        "last_surprise_pct": -449.9
      },
      {
        "code": "4523",
        "name": "エーザイ",
        "sector": "医薬品",
        "next_earnings_date": "2026-08-03",
        "days_until": 17,
        "last_earnings_date": "2026-05-15",
        "last_surprise_pct": -179.1
      },
      {
        "code": "3436",
        "name": "SUMCO",
        "sector": "半導体",
        "next_earnings_date": "2026-08-06",
        "days_until": 20,
        "last_earnings_date": "2026-05-12",
        "last_surprise_pct": -89.7
      },
      {
        "code": "7270",
        "name": "SUBARU",
        "sector": "自動車",
        "next_earnings_date": "2026-08-05",
        "days_until": 19,
        "last_earnings_date": "2026-05-15",
        "last_surprise_pct": -80.8
      },
      {
        "code": "4188",
        "name": "三菱ケミカルG",
        "sector": "素材",
        "next_earnings_date": "2026-07-31",
        "days_until": 14,
        "last_earnings_date": "2026-05-13",
        "last_surprise_pct": -75.2
      },
      {
        "code": "9433",
        "name": "KDDI",
        "sector": "通信・IT",
        "next_earnings_date": "2026-08-07",
        "days_until": 21,
        "last_earnings_date": "2026-05-12",
        "last_surprise_pct": -69.8
      },
      {
        "code": "4689",
        "name": "LINEヤフー",
        "sector": "通信・IT",
        "next_earnings_date": "2026-08-03",
        "days_until": 17,
        "last_earnings_date": "2026-05-08",
        "last_surprise_pct": -63.0
      },
      {
        "code": "6758",
        "name": "ソニーG",
        "sector": "電機",
        "next_earnings_date": "2026-07-31",
        "days_until": 14,
        "last_earnings_date": "2026-05-08",
        "last_surprise_pct": -59.4
      },
      {
        "code": "4568",
        "name": "第一三共",
        "sector": "医薬品",
        "next_earnings_date": "2026-07-31",
        "days_until": 14,
        "last_earnings_date": "2026-05-11",
        "last_surprise_pct": -49.6
      },
      {
        "code": "2502",
        "name": "アサヒグループHD",
        "sector": "生活必需品",
        "next_earnings_date": "2026-07-24",
        "days_until": 7,
        "last_earnings_date": "2026-07-08",
        "last_surprise_pct": -40.7
      }
    ]
  },
  "us_earnings_calendar": [
    {
      "code": "GOOGL",
      "name": "Alphabet",
      "sector": "テクノロジー",
      "next_earnings_date": "2026-07-22",
      "days_until": 5,
      "last_earnings_date": "2026-04-29",
      "last_surprise_pct": 91.6
    },
    {
      "code": "TSLA",
      "name": "Tesla",
      "sector": "消費・EC",
      "next_earnings_date": "2026-07-22",
      "days_until": 5,
      "last_earnings_date": "2026-04-22",
      "last_surprise_pct": 17.1
    },
    {
      "code": "KO",
      "name": "Coca-Cola",
      "sector": "生活必需品",
      "next_earnings_date": "2026-07-28",
      "days_until": 11,
      "last_earnings_date": "2026-04-28",
      "last_surprise_pct": 5.9
    },
    {
      "code": "BA",
      "name": "Boeing",
      "sector": "資本財",
      "next_earnings_date": "2026-07-28",
      "days_until": 11,
      "last_earnings_date": "2026-04-22",
      "last_surprise_pct": 70.3
    },
    {
      "code": "MSFT",
      "name": "Microsoft",
      "sector": "テクノロジー",
      "next_earnings_date": "2026-07-29",
      "days_until": 12,
      "last_earnings_date": "2026-04-29",
      "last_surprise_pct": 4.9
    },
    {
      "code": "META",
      "name": "Meta Platforms",
      "sector": "通信・メディア",
      "next_earnings_date": "2026-07-29",
      "days_until": 12,
      "last_earnings_date": "2026-04-29",
      "last_surprise_pct": 56.8
    },
    {
      "code": "PG",
      "name": "Procter & Gamble",
      "sector": "生活必需品",
      "next_earnings_date": "2026-07-29",
      "days_until": 12,
      "last_earnings_date": "2026-04-24",
      "last_surprise_pct": 2.2
    },
    {
      "code": "AAPL",
      "name": "Apple",
      "sector": "テクノロジー",
      "next_earnings_date": "2026-07-30",
      "days_until": 13,
      "last_earnings_date": "2026-04-30",
      "last_surprise_pct": 3.5
    },
    {
      "code": "AMZN",
      "name": "Amazon",
      "sector": "消費・EC",
      "next_earnings_date": "2026-07-30",
      "days_until": 13,
      "last_earnings_date": "2026-04-29",
      "last_surprise_pct": 68.2
    },
    {
      "code": "XOM",
      "name": "ExxonMobil",
      "sector": "エネルギー",
      "next_earnings_date": "2026-07-31",
      "days_until": 14,
      "last_earnings_date": "2026-05-01",
      "last_surprise_pct": 15.1
    },
    {
      "code": "CVX",
      "name": "Chevron",
      "sector": "エネルギー",
      "next_earnings_date": "2026-07-31",
      "days_until": 14,
      "last_earnings_date": "2026-05-01",
      "last_surprise_pct": 45.6
    },
    {
      "code": "AMD",
      "name": "AMD",
      "sector": "半導体",
      "next_earnings_date": "2026-08-04",
      "days_until": 18,
      "last_earnings_date": "2026-05-05",
      "last_surprise_pct": 5.8
    },
    {
      "code": "CAT",
      "name": "Caterpillar",
      "sector": "資本財",
      "next_earnings_date": "2026-08-04",
      "days_until": 18,
      "last_earnings_date": "2026-04-30",
      "last_surprise_pct": 19.3
    },
    {
      "code": "DIS",
      "name": "Disney",
      "sector": "通信・メディア",
      "next_earnings_date": "2026-08-05",
      "days_until": 19,
      "last_earnings_date": "2026-05-06",
      "last_surprise_pct": 5.0
    },
    {
      "code": "LLY",
      "name": "Eli Lilly",
      "sector": "ヘルスケア",
      "next_earnings_date": "2026-08-05",
      "days_until": 19,
      "last_earnings_date": "2026-04-30",
      "last_surprise_pct": 25.9
    }
  ],
  "us_earnings_rank": {
    "best": [
      {
        "code": "GOOGL",
        "name": "Alphabet",
        "sector": "テクノロジー",
        "next_earnings_date": "2026-07-22",
        "days_until": 5,
        "last_earnings_date": "2026-04-29",
        "last_surprise_pct": 91.6
      },
      {
        "code": "BA",
        "name": "Boeing",
        "sector": "資本財",
        "next_earnings_date": "2026-07-28",
        "days_until": 11,
        "last_earnings_date": "2026-04-22",
        "last_surprise_pct": 70.3
      },
      {
        "code": "AMZN",
        "name": "Amazon",
        "sector": "消費・EC",
        "next_earnings_date": "2026-07-30",
        "days_until": 13,
        "last_earnings_date": "2026-04-29",
        "last_surprise_pct": 68.2
      },
      {
        "code": "META",
        "name": "Meta Platforms",
        "sector": "通信・メディア",
        "next_earnings_date": "2026-07-29",
        "days_until": 12,
        "last_earnings_date": "2026-04-29",
        "last_surprise_pct": 56.8
      },
      {
        "code": "CVX",
        "name": "Chevron",
        "sector": "エネルギー",
        "next_earnings_date": "2026-07-31",
        "days_until": 14,
        "last_earnings_date": "2026-05-01",
        "last_surprise_pct": 45.6
      },
      {
        "code": "GS",
        "name": "Goldman Sachs",
        "sector": "金融",
        "next_earnings_date": "2026-10-13",
        "days_until": 88,
        "last_earnings_date": "2026-07-14",
        "last_surprise_pct": 44.3
      },
      {
        "code": "UNH",
        "name": "UnitedHealth",
        "sector": "ヘルスケア",
        "next_earnings_date": null,
        "days_until": null,
        "last_earnings_date": "2026-07-16",
        "last_surprise_pct": 29.8
      },
      {
        "code": "LLY",
        "name": "Eli Lilly",
        "sector": "ヘルスケア",
        "next_earnings_date": "2026-08-05",
        "days_until": 19,
        "last_earnings_date": "2026-04-30",
        "last_surprise_pct": 25.9
      },
      {
        "code": "CAT",
        "name": "Caterpillar",
        "sector": "資本財",
        "next_earnings_date": "2026-08-04",
        "days_until": 18,
        "last_earnings_date": "2026-04-30",
        "last_surprise_pct": 19.3
      },
      {
        "code": "TSLA",
        "name": "Tesla",
        "sector": "消費・EC",
        "next_earnings_date": "2026-07-22",
        "days_until": 5,
        "last_earnings_date": "2026-04-22",
        "last_surprise_pct": 17.1
      }
    ],
    "worst": [
      {
        "code": "COST",
        "name": "Costco",
        "sector": "生活必需品",
        "next_earnings_date": "2026-09-24",
        "days_until": 69,
        "last_earnings_date": "2026-05-28",
        "last_surprise_pct": 0.1
      },
      {
        "code": "WMT",
        "name": "Walmart",
        "sector": "消費・EC",
        "next_earnings_date": "2026-08-20",
        "days_until": 34,
        "last_earnings_date": "2026-05-21",
        "last_surprise_pct": 0.2
      },
      {
        "code": "NFLX",
        "name": "Netflix",
        "sector": "通信・メディア",
        "next_earnings_date": null,
        "days_until": null,
        "last_earnings_date": "2026-07-16",
        "last_surprise_pct": 1.4
      },
      {
        "code": "JNJ",
        "name": "Johnson & Johnson",
        "sector": "ヘルスケア",
        "next_earnings_date": "2026-10-13",
        "days_until": 88,
        "last_earnings_date": "2026-07-15",
        "last_surprise_pct": 1.6
      },
      {
        "code": "AVGO",
        "name": "Broadcom",
        "sector": "半導体",
        "next_earnings_date": "2026-09-03",
        "days_until": 48,
        "last_earnings_date": "2026-06-03",
        "last_surprise_pct": 1.7
      },
      {
        "code": "PG",
        "name": "Procter & Gamble",
        "sector": "生活必需品",
        "next_earnings_date": "2026-07-29",
        "days_until": 12,
        "last_earnings_date": "2026-04-24",
        "last_surprise_pct": 2.2
      },
      {
        "code": "AAPL",
        "name": "Apple",
        "sector": "テクノロジー",
        "next_earnings_date": "2026-07-30",
        "days_until": 13,
        "last_earnings_date": "2026-04-30",
        "last_surprise_pct": 3.5
      },
      {
        "code": "MSFT",
        "name": "Microsoft",
        "sector": "テクノロジー",
        "next_earnings_date": "2026-07-29",
        "days_until": 12,
        "last_earnings_date": "2026-04-29",
        "last_surprise_pct": 4.9
      },
      {
        "code": "DIS",
        "name": "Disney",
        "sector": "通信・メディア",
        "next_earnings_date": "2026-08-05",
        "days_until": 19,
        "last_earnings_date": "2026-05-06",
        "last_surprise_pct": 5.0
      },
      {
        "code": "NVDA",
        "name": "NVIDIA",
        "sector": "半導体",
        "next_earnings_date": "2026-08-26",
        "days_until": 40,
        "last_earnings_date": "2026-05-20",
        "last_surprise_pct": 5.5
      }
    ]
  },
  "earnings_refreshed_at": "2026-07-17T12:28:10.944471+09:00",
  "btc": 64455.0,
  "btc_pct": -0.53,
  "dxy": 100.75,
  "dxy_pct": 0.02,
  "gold": 4018.8,
  "gold_pct": 0.83,
  "fear_greed_prev": 41.7,
  "fear_greed_diff": -4.6,
  "x_teaser_3line": "今日のSOX-4.3%、正直どこまで日本株に波及するか読み切れてない。\nただ、円安と医薬品のディフェンシブ性がクッションになるんじゃないかと仮定して銘柄を絞ってみた。\nこの読みで合ってるか、外れてたら教えてほしい。",
  "jp_screener": {
    "top": [
      {
        "code": "6301",
        "name": "コマツ",
        "sector": "機械",
        "price": 6251.0,
        "change_pct": -2.93,
        "ma25_diff": -3.5,
        "bb_pos": 15.5,
        "rsi": 46.8,
        "vol_ratio": 0.89,
        "ai_score": 60
      },
      {
        "code": "4452",
        "name": "花王",
        "sector": "生活必需品",
        "price": 3308.0,
        "change_pct": 0.7,
        "ma25_diff": 4.0,
        "bb_pos": 75.5,
        "rsi": 57.5,
        "vol_ratio": 0.78,
        "ai_score": 59
      },
      {
        "code": "7733",
        "name": "オリンパス",
        "sector": "精密機器",
        "price": 1771.5,
        "change_pct": 1.4,
        "ma25_diff": 3.6,
        "bb_pos": 77.1,
        "rsi": 59.9,
        "vol_ratio": 1.02,
        "ai_score": 59
      },
      {
        "code": "8053",
        "name": "住友商事",
        "sector": "商社",
        "price": 1514.0,
        "change_pct": -4.36,
        "ma25_diff": -4.2,
        "bb_pos": 2.2,
        "rsi": 43.5,
        "vol_ratio": 0.96,
        "ai_score": 59
      },
      {
        "code": "6273",
        "name": "SMC",
        "sector": "機械",
        "price": 69230.0,
        "change_pct": -5.72,
        "ma25_diff": -4.5,
        "bb_pos": 10.5,
        "rsi": 46.4,
        "vol_ratio": 1.02,
        "ai_score": 58
      },
      {
        "code": "2502",
        "name": "アサヒグループHD",
        "sector": "生活必需品",
        "price": 1603.0,
        "change_pct": 1.26,
        "ma25_diff": 3.4,
        "bb_pos": 74.5,
        "rsi": 58.5,
        "vol_ratio": 1.04,
        "ai_score": 58
      },
      {
        "code": "2801",
        "name": "キッコーマン",
        "sector": "生活必需品",
        "price": 1667.0,
        "change_pct": 2.14,
        "ma25_diff": 3.0,
        "bb_pos": 78.1,
        "rsi": 54.8,
        "vol_ratio": 0.86,
        "ai_score": 58
      },
      {
        "code": "4543",
        "name": "テルモ",
        "sector": "医療機器",
        "price": 2267.5,
        "change_pct": 2.74,
        "ma25_diff": 1.7,
        "bb_pos": 75.0,
        "rsi": 54.5,
        "vol_ratio": 0.89,
        "ai_score": 57
      },
      {
        "code": "8267",
        "name": "イオン",
        "sector": "小売",
        "price": 1395.0,
        "change_pct": 1.75,
        "ma25_diff": 2.0,
        "bb_pos": 63.9,
        "rsi": 58.9,
        "vol_ratio": 1.09,
        "ai_score": 57
      },
      {
        "code": "6702",
        "name": "富士通",
        "sector": "通信・IT",
        "price": 3298.0,
        "change_pct": 1.26,
        "ma25_diff": 0.5,
        "bb_pos": 55.9,
        "rsi": 56.3,
        "vol_ratio": 1.23,
        "ai_score": 56
      }
    ],
    "bottom": [
      {
        "code": "9433",
        "name": "KDDI",
        "sector": "通信・IT",
        "price": 2868.0,
        "change_pct": 0.84,
        "ma25_diff": 4.5,
        "bb_pos": 96.5,
        "rsi": 70.3,
        "vol_ratio": 0.84,
        "ai_score": 36
      },
      {
        "code": "7974",
        "name": "任天堂",
        "sector": "ゲーム・娯楽",
        "price": 7294.0,
        "change_pct": 3.02,
        "ma25_diff": 3.6,
        "bb_pos": 91.0,
        "rsi": 71.5,
        "vol_ratio": 0.91,
        "ai_score": 36
      },
      {
        "code": "4502",
        "name": "武田薬品工業",
        "sector": "医薬品",
        "price": 5480.0,
        "change_pct": 2.53,
        "ma25_diff": 5.1,
        "bb_pos": 86.7,
        "rsi": 71.2,
        "vol_ratio": 1.01,
        "ai_score": 37
      },
      {
        "code": "5401",
        "name": "日本製鉄",
        "sector": "素材",
        "price": 585.6,
        "change_pct": 0.93,
        "ma25_diff": 5.1,
        "bb_pos": 103.5,
        "rsi": 72.8,
        "vol_ratio": 1.15,
        "ai_score": 37
      },
      {
        "code": "7751",
        "name": "キヤノン",
        "sector": "電機",
        "price": 4466.0,
        "change_pct": 1.57,
        "ma25_diff": 4.8,
        "bb_pos": 102.4,
        "rsi": 75.0,
        "vol_ratio": 1.01,
        "ai_score": 37
      },
      {
        "code": "2914",
        "name": "JT",
        "sector": "生活必需品",
        "price": 6347.0,
        "change_pct": 2.45,
        "ma25_diff": 5.1,
        "bb_pos": 104.9,
        "rsi": 74.4,
        "vol_ratio": 0.88,
        "ai_score": 37
      },
      {
        "code": "3382",
        "name": "セブン&アイHD",
        "sector": "小売",
        "price": 2080.0,
        "change_pct": 3.64,
        "ma25_diff": 5.5,
        "bb_pos": 94.5,
        "rsi": 70.4,
        "vol_ratio": 1.28,
        "ai_score": 38
      },
      {
        "code": "4568",
        "name": "第一三共",
        "sector": "医薬品",
        "price": 2791.0,
        "change_pct": 1.62,
        "ma25_diff": 5.8,
        "bb_pos": 94.2,
        "rsi": 74.5,
        "vol_ratio": 0.9,
        "ai_score": 38
      },
      {
        "code": "4523",
        "name": "エーザイ",
        "sector": "医薬品",
        "price": 4450.0,
        "change_pct": 2.58,
        "ma25_diff": 8.1,
        "bb_pos": 90.0,
        "rsi": 72.7,
        "vol_ratio": 1.03,
        "ai_score": 40
      },
      {
        "code": "7832",
        "name": "バンダイナムコHD",
        "sector": "ゲーム・娯楽",
        "price": 4189.0,
        "change_pct": 1.97,
        "ma25_diff": 8.5,
        "bb_pos": 90.1,
        "rsi": 79.8,
        "vol_ratio": 1.06,
        "ai_score": 40
      }
    ],
    "high_conviction": []
  },
  "us_screener": {
    "top": [
      {
        "code": "GS",
        "name": "Goldman Sachs",
        "sector": "金融",
        "price": 1095.46,
        "change_pct": -4.91,
        "ma25_diff": 3.1,
        "bb_pos": 70.6,
        "rsi": 52.8,
        "vol_ratio": 1.07,
        "ai_score": 58
      },
      {
        "code": "NVDA",
        "name": "NVIDIA",
        "sector": "半導体",
        "price": 207.4,
        "change_pct": -2.4,
        "ma25_diff": 2.2,
        "bb_pos": 67.8,
        "rsi": 57.0,
        "vol_ratio": 0.89,
        "ai_score": 57
      },
      {
        "code": "UNH",
        "name": "UnitedHealth",
        "sector": "ヘルスケア",
        "price": 423.38,
        "change_pct": 1.16,
        "ma25_diff": 1.7,
        "bb_pos": 67.3,
        "rsi": 58.8,
        "vol_ratio": 1.03,
        "ai_score": 57
      },
      {
        "code": "DIS",
        "name": "Disney",
        "sector": "通信・メディア",
        "price": 99.71,
        "change_pct": 2.64,
        "ma25_diff": 1.2,
        "bb_pos": 63.4,
        "rsi": 48.2,
        "vol_ratio": 0.77,
        "ai_score": 56
      },
      {
        "code": "JNJ",
        "name": "Johnson & Johnson",
        "sector": "ヘルスケア",
        "price": 249.97,
        "change_pct": 1.19,
        "ma25_diff": 0.7,
        "bb_pos": 53.8,
        "rsi": 56.6,
        "vol_ratio": 0.91,
        "ai_score": 56
      },
      {
        "code": "PG",
        "name": "Procter & Gamble",
        "sector": "生活必需品",
        "price": 151.5,
        "change_pct": 2.33,
        "ma25_diff": 1.5,
        "bb_pos": 79.7,
        "rsi": 49.2,
        "vol_ratio": 0.83,
        "ai_score": 56
      },
      {
        "code": "LLY",
        "name": "Eli Lilly",
        "sector": "ヘルスケア",
        "price": 1169.17,
        "change_pct": 1.08,
        "ma25_diff": 0.4,
        "bb_pos": 52.8,
        "rsi": 58.0,
        "vol_ratio": 0.78,
        "ai_score": 55
      },
      {
        "code": "COST",
        "name": "Costco",
        "sector": "生活必需品",
        "price": 945.57,
        "change_pct": 3.17,
        "ma25_diff": -0.4,
        "bb_pos": 45.5,
        "rsi": 45.8,
        "vol_ratio": 0.85,
        "ai_score": 55
      },
      {
        "code": "WMT",
        "name": "Walmart",
        "sector": "消費・EC",
        "price": 114.95,
        "change_pct": 2.15,
        "ma25_diff": -0.6,
        "bb_pos": 44.9,
        "rsi": 41.9,
        "vol_ratio": 0.71,
        "ai_score": 54
      },
      {
        "code": "AVGO",
        "name": "Broadcom",
        "sector": "半導体",
        "price": 374.45,
        "change_pct": -5.03,
        "ma25_diff": -2.1,
        "bb_pos": 33.2,
        "rsi": 47.3,
        "vol_ratio": 0.71,
        "ai_score": 53
      }
    ],
    "bottom": [
      {
        "code": "AMZN",
        "name": "Amazon",
        "sector": "消費・EC",
        "price": 249.89,
        "change_pct": -1.99,
        "ma25_diff": 3.4,
        "bb_pos": 82.4,
        "rsi": 65.0,
        "vol_ratio": 0.61,
        "ai_score": 42
      },
      {
        "code": "AAPL",
        "name": "Apple",
        "sector": "テクノロジー",
        "price": 333.26,
        "change_pct": 1.76,
        "ma25_diff": 10.4,
        "bb_pos": 104.5,
        "rsi": 72.1,
        "vol_ratio": 0.72,
        "ai_score": 42
      },
      {
        "code": "MSFT",
        "name": "Microsoft",
        "sector": "テクノロジー",
        "price": 401.1,
        "change_pct": 1.38,
        "ma25_diff": 4.7,
        "bb_pos": 87.8,
        "rsi": 67.8,
        "vol_ratio": 0.65,
        "ai_score": 44
      },
      {
        "code": "CAT",
        "name": "Caterpillar",
        "sector": "資本財",
        "price": 877.17,
        "change_pct": -4.06,
        "ma25_diff": -8.6,
        "bb_pos": 10.0,
        "rsi": 36.6,
        "vol_ratio": 0.63,
        "ai_score": 46
      },
      {
        "code": "KO",
        "name": "Coca-Cola",
        "sector": "生活必需品",
        "price": 84.92,
        "change_pct": 3.0,
        "ma25_diff": 3.5,
        "bb_pos": 94.8,
        "rsi": 63.3,
        "vol_ratio": 0.72,
        "ai_score": 46
      },
      {
        "code": "XOM",
        "name": "ExxonMobil",
        "sector": "エネルギー",
        "price": 145.95,
        "change_pct": 1.0,
        "ma25_diff": 3.8,
        "bb_pos": 82.0,
        "rsi": 69.0,
        "vol_ratio": 0.83,
        "ai_score": 46
      },
      {
        "code": "GE",
        "name": "GE Aerospace",
        "sector": "資本財",
        "price": 345.73,
        "change_pct": -4.06,
        "ma25_diff": -3.3,
        "bb_pos": 29.9,
        "rsi": 36.2,
        "vol_ratio": 0.86,
        "ai_score": 47
      },
      {
        "code": "BAC",
        "name": "Bank of America",
        "sector": "金融",
        "price": 61.49,
        "change_pct": -0.16,
        "ma25_diff": 5.8,
        "bb_pos": 95.7,
        "rsi": 69.0,
        "vol_ratio": 0.99,
        "ai_score": 48
      },
      {
        "code": "AMD",
        "name": "AMD",
        "sector": "半導体",
        "price": 500.94,
        "change_pct": -5.33,
        "ma25_diff": -5.0,
        "bb_pos": 24.3,
        "rsi": 47.3,
        "vol_ratio": 0.82,
        "ai_score": 50
      },
      {
        "code": "CVX",
        "name": "Chevron",
        "sector": "エネルギー",
        "price": 183.86,
        "change_pct": 1.24,
        "ma25_diff": 4.3,
        "bb_pos": 78.4,
        "rsi": 68.9,
        "vol_ratio": 0.69,
        "ai_score": 51
      }
    ],
    "high_conviction": []
  },
  "screener_refreshed_at": "2026-07-17T18:20:35.950582+09:00",
  "weekly_review": {
    "date": "2026/07/18",
    "title": "横ばい相場の中で半導体が輝いた週",
    "note_body": "# 📊 今週の相場振り返り（7/13〜7/17）\n\n## ① 今週の相場総括\n\n日経平均は週初68,557円から週末68,751円へと、わずか+0.28%の横ばいで着地。数字だけ見れば「何も起きなかった週」に見えるかもしれないけど、個別株の世界ではなかなかドラマチックな動きが続いた一週間だった。相場モードはずっと「normal」を維持していて、大きなリスクオフの雰囲気はなかったものの、指数が動かない分だけ銘柄ごとの明暗がくっきり分かれた印象。まさに「指数を見ていても何もわからない」という個別株相場の典型週だったと思う。\n\n## ② 好調だったセクター\n\n今週のMVPはダントツで**半導体**（週間+1.37%）。続いて機械（+0.94%）、自動車（+0.90%）、素材（+0.78%）、通信・IT（+0.40%）と、どちらかといえばシクリカル系・グロース系が強い週だった。半導体は後述の個別銘柄の動きも含め、ボラティリティが高くてトレーダー的には面白い週だったんじゃないかな。機械・自動車の堅調さは円安水準の維持が追い風になっている側面もありそう。\n\n## ③ 不調だったセクター\n\n一方で蚊帳の外だったのが**小売**（−1.25%）、**医療機器**（−0.74%）、**生活必需品**（−0.74%）。グロースや景気敏感が買われる局面でディフェンシブ系が売られるのは典型的なパターン。小売の−1.25%はちょっと痛みを感じるレベル。消費関連の地合いが改善するにはもう少し時間がかかりそうな雰囲気がある。\n\n## ④ 値動きが大きかった銘柄\n\n今週最大の話題は**SUMCO（3436）が+15.4%** という爆発力を見せたこと（5,244円）。半導体シリコンウェーハ大手だけあって、半導体セクター全体の地合いを引っ張る存在感があった。一方で同銘柄は−9.07%（4,614円）という下落も記録しており、週の中でものすごい往復ビンタを食らった形。乗れた人と乗れなかった人で体感がまるで違ったはず。**ソフトバンクG（9984）も+10.65%**（6,370円）と二桁上昇。**レーザーテック（6920）も+10.18%**（49,690円）と強烈な動き。米Goldman Sachsも+9.0%と金融もしっかり。ルネサス（6723）は−7.18%と重かった。\n\n## ⑤ 来週への一言\n\n**「指数が眠っているとき、個別株は起きている。退屈な週ほど、実は一番スキルが試される」**\n\n相場が動かないからこそ、どの銘柄を、どのタイミングで持つかが直結してくる。来週もファンダメンタルズと需給の両方をちゃんと見ながらいきましょう。かぶぼっちは引き続き丁寧に向き合っていきます🌙",
    "discord_summary": "📈【今週の相場まとめ 7/13〜7/17】\n日経平均：68,557→68,751円（+0.28%）ほぼ横ばい\n\n🟢好調：半導体+1.37% / 機械+0.94% / 自動車+0.90%\n🔴不調：小売−1.25% / 医療機器・生活必需品−0.74%\n\n🔥値動き大：SUMCO+15.4%→−9.07%の往復、ソフトバンクG+10.65%、レーザーテック+10.18%\n\n指数は動かなかったけど個別はドラマだらけの一週間でした👀来週もぼちぼちいきましょ🌙"
  },
  "weekly_preview": {
    "date": "2026/07/19",
    "title": "日銀会合×ビッグテック決算、嵐の予感",
    "note_body": "みなさんこんにちは、kabubocchiです。金曜日は日経平均が約4%の大幅下落で週を終えました（終値64,141円）。週明けもボラが高い展開になりそうで、正直ちょっとドキドキしてます。ということで来週の注目ポイントを整理していきます。\n\n**① 最重要イベント：日銀金融政策決定会合（7/22）**\n来週最大の注目はなんといっても7月22日の日銀会合です。展望レポートも同時に発表される重要会合。今の円相場・物価動向を踏まえ、市場は利上げの有無を神経質に織り込みにいくとみられます。結果次第では為替・金利が大きく動き、株式市場全体に影響が出る可能性があるので、ポジション管理はいつも以上に慎重にいきたいところです。\n\n**② 注目決算ラッシュ（7/22〜7/24）**\n米国では7月22日にAlphabet（GOOGL）とTesla（TSLA）が決算発表予定。Alphabetは前回なんと約+91.6%のサプライズを叩き出した実績があり、市場の期待値は相当高い。ここで期待を裏切ると調整リスクもあるので注意。Teslaも前回+17.1%のポジティブサプライズ。引き続き結果次第でナスダック全体の雰囲気を左右しそうです。\n\n国内では7月24日に信越化学、中外製薬、アサヒグループHDが登場。注目はアサヒグループHD、前回決算でサプライズが-40.7%と厳しい結果でした。今回どこまで挽回できるか、ガイダンスの修正も含めて要チェックです。信越化学も前回-10.9%と低調だっただけに、ここで反転できるか見極めたいですね。\n\n**③ 値動きシナリオ（あくまで個人の見立て）**\n日銀会合の結果が市場予想に沿ったものであれば、いったん「材料出尽くし」的な動きになる可能性もあります。一方、想定外のタカ派or急なトーン変化があれば、円高・株安の展開も考えられます。米国決算も複数のビッグテックが重なるため、NYの動きが翌日の日本株に跳ね返ってくる構図は意識しておきたいです。\n\n**④ かぶぼっちの一言**\nイベント盛りだくさんな週は「嵐の前後どちらにいるか」を常に意識する。フルポジで突っ込む週じゃないと個人的には思ってます。生き残ってこそ、ですよ。お互いうまく乗り切りましょう！",
    "discord_summary": "【来週の注目まとめ】\n📌 最重要：日銀会合（7/22）展望レポートも発表。利上げ姿勢次第で為替・株全体が動く可能性あり\n📌 米国決算：Alphabet・Tesla（7/22）前回大幅サプライズのAlphabetに注目\n📌 国内決算：信越化学・中外製薬・アサヒG（7/24）前回不振のアサヒGが巻き返せるか\n⚠️金曜日経は-4%超の下落。ボラ高い週になりそうなのでポジション管理をしっかりと！"
  },
  "strategy_lines": [
    "1. 半導体・製造装置系（東京エレクトロン・信越化学・キーエンス）は追加下落リスクを織り込み、現値からの飛び乗りは避け、明確な下げ止まりサインを確認してからの打診買いに限定する。",
    "2. 医薬品（第一三共・中外製薬）はSOXショックの影響を受けにくいディフェンシブ性が相対的に高く、前営業日の強さを踏まえてモメンタム戦略の候補として注目する。ただし過熱シグナルが出たら一旦引く判断を先に用意しておくこと。",
    "3. RSI70超・BB上限の高値圏銘柄（三菱UFJ・JT・NTT等）は新規買いよりも保有者の利益確定タイミングを意識し、無理に追いかけず次の押し目を待つ姿勢を基本とする。",
    "4. 円安162円台を活かした輸出・自動車セクター（本田技研・トヨタ）は押し目でのエントリーを意識しつつ、急激な円高反転リスクに備えてストップロスを明確に設定してからポジションを建てる。",
    "5. 今日は欲張らず「1〜2銘柄・小さめロット」のルールで臨み、SOXショックの余波がどこまで広がるかを前場で見極めてから後場に動くというタイムマネジメントも有効な選択肢だ。"
  ],
  "nikkei_data_stale": false,
  "jp_sector_heatmap_stale": false,
  "jp_sector_heatmap_refreshed_at": "2026-07-20T05:46:02.971577+09:00",
  "us_sector_heatmap_stale": false,
  "us_sector_heatmap_refreshed_at": "2026-07-20T05:46:02.971577+09:00"
}